Workbook

Sheet Readme
A1: Búsqueda de palabras clave para detectar obligaciones
A2: debe
A3: deberá
A4: prestará
A5: estará
A6: le corresponderá
A7: será obligación
A8: podrá | B8: Se refiere a atribución que puede o no hacer
A10: Referencias consultadas y personas influyentes
A11: José Inostroza | B11: Gobierno Digital
A12: Claudio Reyes | B12: Secretaría de Modernización
A13: Daniel Álvarez | B13: U de Chile
A14: Alejandro Barros | B14: U de Chile
A15: Pilar Díaz Ellis | B15: Archivo Nacional
A16: Gabriela Andaur | B16: Archivo Nacional
A17: Allen Guerra | B17: BCN
A18: Carla Illanes Contreras | B18: DLA Piper Chile
A19: Rosa Gómez | B19: U de Los Andes | C19: https://www.uandes.cl/personas/gomez-gonzalez-rosa-fernanda/
A20: Romina Garrido | B20: GobLab UAI
A21: Sergio Bijman | B21: TakeUp
A22: Renato Jijena | B22: PUCV
A23: Andrés Pumarino | B23: LegalTrust
A25: En el registro los párrafos que contienen más de una obligación se repiten para mantener una obligación por fila.
A26: En las normas técnicas pueden haber imágenes que no son transferidas al registro
A28: Lecciones
A29: Todo debe ir al formato de la BCN, porque cumple estándares. Evitar el uso de pdf o cualquier otro archivo que no se pueda leer como texto directo desde el sitio Web.
A30: Las leyes y reglamentos se actualizan en la BCN, por lo que se debe mirar la fecha de obtención y carga en la base de Normativa.
A32: Ayuda a visibilizar normativa que puede estar omitiéndose del ecosistema de la Ley Nº 21.180
A34: Retroalimentación para la BCN
A35: Mal separados o que pudieran tener una mejor organización
A36: Decreto MINDEF Política de ciberdefensa 2018-3
A38: Grupo A | B38: Ministerios; Servicios Públicos; Contraloría General de la República; Fuerzas Armadas; Fuerzas de Orden y Seguridad; y delegaciones presidenciales regionales provinciales.
A39: Grupo B | B39: Gobiernos Regionales y Municipios de clasificación 1 y 2
A40: Grupo C | B40: Municipios clasificados en los grupos de categoría 3,4 y 5 (Subdere)
A42: 1. Comunicaciones oficiales entre los órganos de la Administración del Estado | B42: 1. Comunicaciones oficiales entre los órganos de la Administración del Estado: Dichas comunicaciones deberán realizarse según lo dispuesto en el inciso sexto del artículo 19 de la ley Nº 19.880 y su respectivo reglamento.
A43: 2. Notificaciones | B43: 2. Notificaciones: La copia de todas las notificaciones que se realicen dentro de un procedimiento administrativo se incluirán en el Domicilio Digital Único de los interesados, que regulan los artículos 30 y 46 de la ley Nº 19.880 y su respectivo reglamento. Lo señalado en el párrafo anterior en ningún caso reemplazará a la notificación realizada por el medio establecido por la ley especial.
A44: 3. Registro de actuaciones en expedientes electrónicos | B44: 3. Registro de actuaciones en expedientes electrónicos: las actuaciones realizadas por medios distintos al electrónico se deberán registrar, debiendo para ello digitalizarlas e incluirlas en el expediente electrónico respectivo, según lo dispuesto en el inciso segundo del artículo 1º, los incisos tercero y sexto del artículo 18 y en el artículo 19 de la ley Nº 19.880 y su respectivo reglamento.
A45: 4. Principio de interoperabilidad | B45: 4. Principio de interoperabilidad: este principio se ajustará a lo dispuesto en los incisos segundo y quinto del artículo 16 bis de la ley Nº 19.880 y su respectivo reglamento.
A47: Fase de Preparación | B47: Cada órgano de la Administración deberá identificar y describir las etapas de los procedimientos administrativos que desarrolla, y en particular la necesidad de notificación en cada uno de ellos. La División de Gobierno Digital del Ministerio Secretaría General de la Presidencia entregará las orientaciones técnicas respecto de esta fase. | C47: =A47&": "&B47 -> Fase de Preparación: Cada órgano de la Administración deberá identificar y describir las etapas de los procedimientos administrativos que desarrolla, y en particular la necesidad de notificación en cada uno de ellos. La División de Gobierno Digital del Ministerio Secretaría General de la Presidencia entregará las orientaciones técnicas respecto de esta fase.
A48: Fase 1 Comunicaciones oficiales | B48: Las comunicaciones oficiales entre los órganos de la Administración serán registradas en una plataforma electrónica destinada al efecto, en virtud de lo dispuesto en el inciso sexto del artículo 19 de la ley Nº 19.880. | C48: =A48&": "&B48 -> Fase 1 Comunicaciones oficiales: Las comunicaciones oficiales entre los órganos de la Administración serán registradas en una plataforma electrónica destinada al efecto, en virtud de lo dispuesto en el inciso sexto del artículo 19 de la ley Nº 19.880.
A49: Fase 2 Notificaciones electrónicas | B49: Las notificaciones se practicarán por medios electrónicos, en virtud de lo dispuesto en los artículos 30 y 46 de la ley Nº 19.880. | C49: =A49&": "&B49 -> Fase 2 Notificaciones electrónicas: Las notificaciones se practicarán por medios electrónicos, en virtud de lo dispuesto en los artículos 30 y 46 de la ley Nº 19.880.
A50: Fase 3 Principio de interoperabilidad | B50: El ingreso de las solicitudes, formularios o documentos, se hará mediante documentos electrónicos o por medio de formatos electrónicos a través de las plataformas de los órganos de la Administración del Estado, en virtud de lo dispuesto en el inciso cuarto del artículo 18, y en el inciso cuarto del artículo 30 de la ley Nº 19.880. | C50: =A50&": "&B50 -> Fase 3 Principio de interoperabilidad: El ingreso de las solicitudes, formularios o documentos, se hará mediante documentos electrónicos o por medio de formatos electrónicos a través de las plataformas de los órganos de la Administración del Estado, en virtud de lo dispuesto en el inciso cuarto del artículo 18, y en el inciso cuarto del artículo 30 de la ley Nº 19.880.
A51: Fase 4 Expedientes electrónicos | B51: El procedimiento administrativo deberá constar en expedientes electrónicos, en virtud de lo dispuesto en el inciso segundo del artículo 1º, en el artículo 5º, en el inciso cuarto del artículo 16 bis, en los incisos tercero y sexto del artículo 18, en el artículo 19 y en el artículo 25 inciso final de la ley Nº 19.880. | C51: =A51&": "&B51 -> Fase 4 Expedientes electrónicos: El procedimiento administrativo deberá constar en expedientes electrónicos, en virtud de lo dispuesto en el inciso segundo del artículo 1º, en el artículo 5º, en el inciso cuarto del artículo 16 bis, en los incisos tercero y sexto del artículo 18, en el artículo 19 y en el artículo 25 inciso final de la ley Nº 19.880.
A52: Fase 5 Digitalización del documento en papel | B52: Las solicitudes, formularios o escritos presentados en soporte de papel serán digitalizados e ingresados al expediente electrónico inmediatamente por el funcionario correspondiente, en virtud de lo dispuesto en los artículos 18 y 19 bis de la ley Nº 19.880. | C52: =A52&": "&B52 -> Fase 5 Digitalización del documento en papel: Las solicitudes, formularios o escritos presentados en soporte de papel serán digitalizados e ingresados al expediente electrónico inmediatamente por el funcionario correspondiente, en virtud de lo dispuesto en los artículos 18 y 19 bis de la ley Nº 19.880.
B55: Grupo A | C55: Grupo B | D55: Grupo C | F55: RUTA / Acciones a realizar | G55: 44713 | H55: 44743 | I55: 44774 | J55: 44805 | K55: 44835 | L55: 44866 | M55: 44896 | N55: 44927 | O55: 44958 | P55: 44986 | Q55: 45017 | R55: 45047 | S55: 45078 | T55: 45108 | U55: 45139 | V55: 45170 | W55: 45200 | X55: 45231 | Y55: 45261 | Z55: 45292 | AA55: 45323 | AB55: 45352 | AC55: 45383 | AD55: 45413 | AE55: 45444 | AF55: 45474 | AG55: 45505 | AH55: 45536 | AI55: 45566 | AJ55: 45597 | AK55: 45627
A56: 2022 | B56: Preparación | C56: Preparación | D56: Preparación | F56: RUTA DE IDENTIFICACIÓN DE PROCEDIMIENTOS ADMINISTRATIVOS
A57: 2023 | B57: 1 | C57: Preparación | D57: Preparación | F57: Entre el 31 de Enero y el 14 de Febrero, deberán hacer llegar el avance en el formato solicitado por Gobierno Digital. Para informar este primer hito de avance de la fase de preparación, se disponibilizará la plataforma de seguimiento de la Ley. | O57: 1
A58: 2024 | B58: 3 | C58: 1 | D58: 1 | F58: Período orientado a refinar la nómina y profundizar la caracterización de los Procedimientos Administrativos levantados, siguiendo las recomendaciones entregadas por Gobierno Digital durante este período. | O58: 1 | P58: 1 | Q58: 1 | R58: 1 | S58: 1 | T58: 1 | U58: 1 | V58: 1
A59: 2025 | B59: 6 | C59: 3 y 6 | D59: 3 | F59: Período de levantamiento de línea de base de procedimientos administrativos en la plataforma en línea “Catálogo de Procedimientos Administrativos y Trámites” (CPAT). | W59: 1 | X59: 1 | Y59: 1
A60: 2026 | B60: 2, 4 y 5 | C60: 4 y 5 | D60: 4 y 6 | F60: Se establecerán períodos durante el año para ajustar y actualizar la información de los procedimientos administrativos de los órganos. | Z60: 1 | AA60: 1 | AB60: 1 | AC60: 1 | AD60: 1 | AE60: 1 | AF60: 1 | AG60: 1 | AH60: 1 | AI60: 1 | AJ60: 1 | AK60: 1
A61: 2027 | C61: 2 | D61: 2 y 5 | F61: RUTA DE COMUNICACIONES OFICIALES (DocDigital)
F62: Aquellos órganos no usuarios de la plataforma, deberán iniciar el proceso de integración y uso de la herramienta. Mientras que aquellos órganos ya integrados, deberán trabajar en aumentar la cobertura de su uso para que la totalidad de sus comunicaciones oficiales, se realice mediante DocDigital. | G62: 1 | H62: 1 | I62: 1 | J62: 1 | K62: 1 | L62: 1 | M62: 1
F63: Aquellos órganos ya integrados deberán trabajar en aumentar la cobertura de su uso para que la totalidad de sus comunicaciones se realice a través de la plataforma. | Q63: 1 | R63: 1 | S63: 1 | T63: 1 | U63: 1 | V63: 1 | W63: 1 | X63: 1 | Y63: 1
A64: a) Grupo A. | F64: RUTA DE INTEROPERABILIDAD Y GOBERNANZA DE DATOS
A65: (i) Los ministerios. | F65: Los órganos que están interoperando en la actual Plataforma de Interoperabilidad (PISEE 1.0) contarán con el apoyo técnico de Gobierno Digital para: Instalar y comenzar a usar el Nodo de Interoperabilidad y Registrar en el Catálogo de Servicios | G65: 1 | H65: 1 | I65: 1 | J65: 1 | K65: 1 | L65: 1 | M65: 1
A66: (ii) Los servicios públicos creados para el cumplimiento de la función administrativa, que no se encuentren en los grupos B y C. | F66: Se comenzará a apoyar a los órganos del Grupo A, que interoperan y no son usuarios de PISEE 1.0 para efectos de: Instalar y comenzar a usar el Nodo de Interoperabilidad Publicar sus servicios web en el Catálogo de Servicios. | N66: 1 | O66: 1 | P66: 1 | Q66: 1 | R66: 1 | S66: 1 | T66: 1 | U66: 1 | V66: 1 | W66: 1 | X66: 1 | Y66: 1
A67: (iii) La Contraloría General de la República. | F67: RUTA DE MECANISMOS OFICIALES DE AUTENTICACIÓN
A68: (iv) Las Fuerzas Armadas y las Fuerzas de Orden y Seguridad Pública. | F68: Deshabilitar progresivamente los mecanismos de autenticación diferentes a ClaveÚnica para personas naturales. Esta medida no aplica para PA de gestión interna que solo involucran a funcionarios. | N68: 1 | O68: 1 | P68: 1 | Q68: 1 | R68: 1 | S68: 1 | T68: 1 | U68: 1 | V68: 1 | W68: 1 | X68: 1 | Y68: 1
A69: (v) Las delegaciones presidenciales regionales y provinciales. | F69: RUTA DE PLANES DE TRANSFORMACIÓN DIGITAL Y CALIDAD DE LAS PLATAFORMAS
F70: Identificar las plataformas electrónicas que soportan sus procedimientos administrativos. | G70: 1 | H70: 1 | I70: 1 | J70: 1 | K70: 1 | L70: 1 | M70: 1
A71: b) Grupo B. | F71: Priorizar las plataformas, identificar modelo de calidad para cada plataforma, seleccionar características, subcaracterísticas, métricas, fórmulas y umbrales. | P71: 1 | Q71: 1 | R71: 1
A72: (i) Los gobiernos regionales. | F72: Materializar el Plan de Transformación Digital y mejora continua de sus plataformas. La planificación debe identificar las plataforma y proponer las iniciativas y proyectos necesarios para su implementación. | R72: 1 | S72: 1
A73: (ii) Los siguientes municipios: Alto Hospicio, Antofagasta, Arica, Buin, Calama, Calera, Cartagena, Cerrillos, Cerro Navia, Chiguayante, Chillán, Chillán Viejo, Colina, Concepción, Conchalí, Concón, Copiapó, Coquimbo, Coronel, Coyhaique, Curicó, El Bosque, El Tabo, Estación Central, Hualpén, Huechuraba, Independencia, Iquique, La Cisterna, La Cruz, La Florida, La Granja, La Pintana, La Reina, La Serena, Lampa, Las Condes, Lo Barnechea, Lo Espejo, Lo Prado, Los Ángeles, Lota, Machalí, Macul, Maipú, Ñuñoa, Osorno, Padre Hurtado, Pedro Aguirre Cerda, Penco, Peñaflor, Peñalolén, Pirque, Providencia, Pudahuel, Puente Alto, Puerto Montt, Puerto Varas, Punta Arenas, Quilicura, Quillota, Quilpué, Quinta Normal, Rancagua, Recoleta, Renca, San Antonio, San Bernardo, San Joaquín, San Miguel, San Pedro de la Paz, San Ramón, Santiago, Santo Domingo, Talagante, Talca, Talcahuano, Temuco, Tomé, Valdivia, Valparaíso, Villa Alemana, Viña del Mar y Vitacura. | F73: Deberán presentar los proyectos del plan que se deberán ejecutar el año 2024 en el marco del proceso de Evaluación de Proyectos (evalTIC), donde se pondrá especial atención a aquellos proyectos cuya justificación esté amparado en sus planes de Transformación Digital y de mejora continua de sus plataformas. | S73: 1 | T73: 1
A75: c) Grupo C.
A76: (i) Los siguientes municipios: Algarrobo, Alhué, Alto Biobío, Alto del Carmen, Ancud, Andacollo, Angol, Antuco, Arauco, Aysén, Bulnes, Cabildo, Cabo de Hornos (Ex-Navarino), Cabrero, Calbuco, Caldera, Calera de Tango, Calle Larga, Camarones, Camiña, Canela, Cañete, Carahue, Casablanca, Castro, Catemu, Cauquenes, Chaitén, Chanco, Chañaral, Chépica, Chile Chico, Chimbarongo, Cholchol, Chonchi, Cisnes, Cobquecura, Cochamó, Cochrane, Codegua, Coelemu, Coihueco, Coinco, Colbún, Colchane, Collipulli, Coltauco, Combarbalá, Constitución, Contulmo, Corral, Cunco, Curacautín, Curacaví, Curaco de Vélez, Curanilahue, Curarrehue, Curepto, Dalcahue, Diego de Almagro, Doñihue, El Carmen, El Monte, El Quisco, Empedrado, Ercilla, Florida, Freire, Freirina, Fresia, Frutillar, Futaleufú, Futrono, Galvarino, General Lagos, Gorbea, Graneros, Guaitecas, Hijuelas, Hualaihué, Hualañé, Hualqui, Huara, Huasco, Illapel, Isla de Maipo, Isla de Pascua, Juan Fernández, La Estrella, La Higuera, La Ligua, La Unión, Lago Ranco, Lago Verde, Laguna Blanca, Laja, Lanco, Las Cabras, Lautaro, Lebu, Licantén, Limache, Linares, Litueche, Llaillay, Llanquihue, Lolol, Loncoche, Longaví, Lonquimay, Los Álamos, Los Andes, Los Lagos, Los Muermos, Los Sauces, Los Vilos, Lumaco, Máfil, Malloa, Marchihue, María Elena, María Pinto Mariquina, Maule, Maullín, Mejillones, Melipeuco, Melipilla, Molina, Monte Patria, Mostazal, Mulchén, Nacimiento, Nancagua, Natales, Navidad, Negrete, Ninhue, Nogales, Nueva Imperial, Ñiquén, O'Higgins, Olivar, Ollagüe, Olmué, Ovalle, Padre Las Casas, Paiguano, Paillaco, Paine, Palena, Palmilla, Panguipulli, Panquehue, Papudo, Paredones, Parral, Pelarco, Pelluhue, Pemuco, Pencahue, Peralillo, Perquenco, Petorca, Peumo, Pica, Pichidegua, Pichilemu, Pinto, Pitrufquén, Placilla, Portezuelo, Porvenir, Pozo Almonte, Primavera, Puchuncaví, Pucón, Puerto Octay, Pumanque, Punitaqui, Puqueldón, Purén, Purranque, Putaendo, Putre, Puyehue, Queilén, Quellón, Quemchi, Quilaco, Quilleco, Quillón, Quinchao, Quinta de Tilcoco, Quintero, Quirihue, Ranquil, Rauco, Renaico, Rengo, Requínoa, Retiro, Rinconada, Río Bueno, Río Claro, Río Hurtado, Río Ibáñez, Río Negro, Río Verde, Romeral, Saavedra, Sagrada Familia, Salamanca, San Carlos, San Clemente, San Esteban, San Fabián, San Felipe, San Fernando, San Gregorio, San Ignacio, San Javier, San José de Maipo, San Juan de la Costa, San Nicolás, San Pablo, San Pedro, San Pedro de Atacama, San Rafael, San Rosendo, San Vicente, Santa Bárbara, Santa Cruz, Santa Juana, Santa María, Sierra Gorda, Taltal, Teno, Teodoro Schmidt, Tierra Amarilla, Tiltil, Timaukel, Tirúa, Tocopilla, Toltén, Torres del Paine, Tortel, Traiguén, Trehuaco, Tucapel, Vallenar, Vichuquén, Victoria, Vicuña, Vilcún, Villa Alegre, Villarrica, Yerbas Buenas, Yumbel, Yungay y Zapallar.
A78: datos.gob: 531 organizaciones
A79: gob digital: 615 Instituciones que integran Clave Única
A80: gob digital: CERO PAPEL 616 Oficinas de partes Registradas en DocDigital
A81: innovadores públicos: ¿?
A82: Mercado público: | B82: https://datos-abiertos.chilecompra.cl/descargas/complementos
A85: N° pregunta | B85: Pregunta | C85: Descripción pregunta | D85: Tipo de respuesta | E85: Alternativas de respuesta | F85: Observaciones
A86: P.1 | B86: Nombre del órgano de la Administración del Estado | C86: Nombre que corresponda a su institución | D86: Abierta | E86: Campo de texto libre
A87: P.2 | B87: Nombre del procedimiento administrativo | C87: Nombre o denominación que identifica al procedimiento administrativo | D87: Abierta | E87: Campo de texto libre
A88: P.3 | B88: Descripción y/o alcance del procedimiento administrativo | C88: Breve descripción de los aspectos abarca o caracterizan al procedimiento administrativo | D88: Abierta | E88: Campo de texto libre
A89: P.4 | B89: Área de dependencia dentro del OAE | C89: Área o dependencia interna a la cual pertenece el procedimiento administrativo. Es posible que un procedimiento administrativo aplique a varias áreas o dependencias, sin embargo, se recomienda seleccionar aquella que tenga mayor jerarquía sobre el procedimiento administrativo | D89: Selección única (lista desplegable) | F89: No debe ser respondida por las municipalidades
A90: P.5 | B90: Área de dependencia dentro del municipio | C90: En el caso de que su institución sea una municipalidad, deberá escoger de la lista desplegable el nombre del área o dependencia municipal a la cual pertenece el procedimiento administrativo. Es posible que un procedimiento administrativo aplique a varias áreas o dependencias, sin embargo se recomienda seleccionar aquella que tenga mayor jerarquía sobre el procedimiento administrativo | D90: Selección única (lista desplegable) | F90: Sólo debe ser respondida por las municipalidades
A91: P.6 | B91: Tipo de inicio del procedimiento administrativo | C91: Deberá indicar si inicia de oficio, es decir como parte de la gestión que realiza la propia institución, o a solicitud del interesado, pudiendo ser éste una persona natural, jurídica u otro órgano de la administración del Estado | D91: Selección única (lista desplegable) | E91: De oficio/ Solicitud de partes
A92: P.7 | B92: Naturaleza del procedimiento administrativo | C92: Deberá especificar si se trata de un procedimiento de gestión interna, es decir que no involucra interacciones con externos, sean estas personas naturales, jurídicas o otros órganos de la administración del Estado, o si el flujo involucra interacción con externos o terceros, independiente de la naturaleza de ellos | D92: Selección única (lista desplegable) | E92: Interno/ Externo
A93: P.8 | B93: Nivel de digitalización | C93: Un procedimiento administrativo no es digital cuando ninguna de sus etapas cuenta con un soporte electrónico. Se considerará que el procedimiento administrativo es parcialmente digital cuando al menos una de sus etapas disponga de un soporte electrónico, sin embargo, persistan una o más etapas en soporte análogo. Finalmente, el procedimiento administrativo se considerará completamente digital cuando todas las etapas cuenten con un soporte electrónico | D93: Selección única (lista desplegable) | E93: No es digital/ Parcialmente digital/ Completamente digital
A94: P.9 | B94: Tipo de fuente normativa del procedimiento administrativo | C94: Deberá identificar si la fuente normativa que le aplica al procedimiento administrativo es una Ley, Norma o Decreto | D94: Selección única (lista desplegable) | E94: Ley/ Norma/ Decreto
A95: P.10 | B95: Fuente normativa del procedimiento administrativo | C95: Deberá identificar el número del instrumento normativo que le aplica al procedimiento administrativo, por ejemplo la Ley 20.285 | D95: Abierta | E95: Campo de texto libre
A96: P.11 | B96: Link de la fuente normativa | C96: Deberá identificar el enlace a Ley Chile del instrumento normativo que le aplica al procedimiento administrativo | D96: Abierta | E96: Campo de texto libre
A97: P.12 | B97: ¿La PA requiere un mecanismo de autenticación? | C97: Deberá identificar si el procedimiento administrativo requiere un mecanismo de autenticación, es decir, requiere de métodos o un conjunto de procesos que permitan validar los datos e identificación de un usuario con un nivel de confianza conocido. Entre las opciones disponibles se encuentra: a) No requiere un mecanismo de autenticación, b) utiliza ClaveÚnica como mecanismo de autenticación (servicio compartido provisto por la División de Gobierno Digital), c) utiliza Clave Tributaria como mecanismo de autenticación (servicio provisto por Servicio de Impuestos Internos), d) utiliza un mecanismo de autenticación propio de la institución, o e) utiliza ClaveÚnica y/o Clave Tributaria y/o un mecanismo propio como mecanismo de autenticación. | D97: Selección única (lista desplegable) | E97: No utiliza mecanismo de autenticación/ Utiliza ClaveÚnica/ Utiliza Clave Tributaria/ Utiliza un mecanismo de autenticación propio/ Utiliza más de un mecanismo de autenticación (clave tributaria y/o claveúnica y/o un mecanismo propio)
A98: P.13 | B98: ¿Requiere datos y/o documentos de privados? | C98: Deberá identificar si el procedimiento administrativo utiliza o no datos y/o documentos dispuestos por privados, por ejemplo un certificado emitido por una administradora de fondos de pensiones. | D98: Selección única (lista desplegable) | E98: Si/No
A99: P.14 | B99: ¿Requiere datos y/o documentos de otros OAE? | C99: Deberá identificar si el procedimiento administrativo requiere la utilización o no de datos y/o documentos dispuestos por otros órganos de la administración del Estado, tales como subsecretarías, servicios públicos, gobiernos regionales, delegaciones presidenciales y provinciales, municipalidades, entre otros. | D99: Selección única (lista desplegable) | E99: Si/No
A100: P.15 | B100: Indique el tipo de interoperabilidad utilizado | C100: Si contesta sí a la pregunta anterior (P.14), deberá indicar el tipo de interoperabilidad utilizado para compartir datos y/o documentos con otros órganos de la administración del Estado según corresponda. | D100: Selección única (lista desplegable) | E100: No interopero (aún se le debe solicitar a la persona el documento) PISEE/ PISEE 2 (Nodo)/ Sistemas propios para interoperar con otros OAE
A101: P.16 | B101: ¿Requiere Firma electrónica? | C101: Deberá identificar si el procedimiento administrativo utiliza o no durante su tramitación firma electrónica avanzada, para cualquiera de sus gestiones. | D101: Selección única (lista desplegable) | E101: Si/No
A102: P.17 | B102: ¿El PA genera un expediente? | C102: Deberá identificar si el procedimiento administrativo genera o no un expediente electrónico, el cual contiene el conjunto de documentos electrónicos correspondiente al procedimiento administrativo. | D102: Selección única (lista desplegable) | E102: Si/No
... A106: P.21 | B106: URL de la plataforma electrónica | C106: Deberá informar la URL de la plataforma electrónica que soporta el procedimiento administrativo | D106: Abierta | E106: Campo de texto libre

Sheet Normativa
B2: =SUM(B5:B102) -> 12769
A3: ID_normativa | B3: Carga | C3: Tipo de normativa | D3: Acción | E3: Acción_que_realiza_a | F3: Link | G3: Responsable | H3: Materia | I3: Fecha_de_Publicación | J3: Fecha de obtención | K3: Texto | L3: Complemento_texto_1 | M3: Complemento_texto_2 | N3: Origen de la norma | O3: Complemento_origen
B4: =if(A4="","", countif(Obligaciones!$D$3:$D$20388,A4))
A5: Ley 19799 | B5: =if(A5="","", countif(Obligaciones!$D$3:$D$20388,A5)) -> 184 | C5: Ley | D5: Original | F5: https://bcn.cl/2f6mw | G5: Ministerio de Economía, Fomento y Reconstrucción | H5: Sobre documentos electrónicos, firma electrónica y servicios de certificación de dicha firma | I5: 37358 | J5: 45064 | K5: Ley 19.799: Sobre Documentos Electrónicos, Firma Electrónica y Servicios de Certificación de Dicha Firma. | L5: Fecha de publicación: v.Año: 2002 | M5: Establece la forma en que las instituciones del Estado deben llevar a... | N5: https://digital.gob.cl/biblioteca/regulacion/
A6: Decreto MINECON 2002-181 | B6: =if(A6="","", countif(Obligaciones!$D$3:$D$20388,A6)) -> 369 | C6: Reglamento | D6: Original | F6: https://bcn.cl/3cxw0 | G6: Ministerio de Economía, Fomento y Reconstrucción | H6: Sobre documentos electrónicos, firma electrónica y servicios de certificación de dicha firma | I6: 37485 | J6: 45064 | K6: Decreto Nº181 DECRETO 181 APRUEBA REGLAMENTO DE LA LEY 19.799 SOBRE DOCUMENTOS ELECTRONICOS, FIRMA ELECTRONICA Y LA CERTIFICACION DE DICHA FIRMA. MINISTERIO DE ECONOMÍA; FOMENTO Y RECONSTRUCCION; SUBSECRETARIA DE ECONOMIA; FOMENTO Y RECONSTRUCCION | L6: Fecha de publicación: v.Año: 2002 | M6: Reglamento de la Ley Nº 19.799 sobre documentos electrónicos, firma... | N6: https://digital.gob.cl/biblioteca/regulacion/
A7: Decreto MINECON 2006-348 | B7: =if(A7="","", countif(Obligaciones!$D$3:$D$20388,A7)) -> 0 | C7: Reglamento | D7: Modifica a | E7: Decreto MINECON 2002-181 | F7: https://bcn.cl/3cxvy | G7: Ministerio de Economía, Fomento y Reconstrucción | H7: Sobre documentos electrónicos, firma electrónica y servicios de certificación de dicha firma | I7: 38749 | J7: 45064 | K7: DECRETO 348 MODIFICA DECRETO Nº 181, DE 2002 MINISTERIO DE ECONOMÍA; FOMENTO Y RECONSTRUCCION; SUBSECRETARIA DE ECONOMIA; FOMENTO Y RECONSTRUCCION | N7: BCN
A8: Decreto MINECON 2012-154 | B8: =if(A8="","", countif(Obligaciones!$D$3:$D$20388,A8)) -> 0 | C8: Reglamento | D8: Modifica a | E8: Decreto MINECON 2002-181 | F8: https://bcn.cl/3cxw1 | G8: Ministerio de Economía, Fomento y Reconstrucción | H8: Sobre documentos electrónicos, firma electrónica y servicios de certificación de dicha firma | I8: 41132 | J8: 45064 | K8: 11-AGO-2012 DECRETO 154 - ARTÍCULO PRIMERO. MODIFICA DECRETO N° 181, DE 2002, QUE APRUEBA REGLAMENTO DE LA LEY Nº 19.799 SOBRE DOCUMENTOS ELECTRÓNICOS, FIRMA ELECTRÓNICA Y LA CERTIFICACIÓN DE DICHA FIRMA. MINISTERIO DE ECONOMÍA, FOMENTO Y TURISMO;SUBSECRETARÍA DE ECONOMÍA Y EMPRESAS DE MENOR TAMAÑO | N8: BCN
A9: Decreto MINECON 2014-14 | B9: =if(A9="","", countif(Obligaciones!$D$3:$D$20388,A9)) -> 0 | C9: Reglamento | D9: Modifica a | E9: Decreto MINECON 2002-181 | F9: https://bcn.cl/2r3hy | G9: Ministerio de Economía, Fomento y Reconstrucción | H9: Sobre documentos electrónicos, firma electrónica y servicios de certificación de dicha firma | I9: 41697 | J9: 45064 | K9: DECRETO 14 MODIFICA DECRETO Nº 181, DE 2002, QUE APRUEBA REGLAMENTO DE LA LEY 19.799 SOBRE DOCUMENTOS ELECTRÓNICOS, FIRMA ELECTRÓNICA Y LA CERTIFICACIÓN DE DICHA FIRMA, Y DEROGA LOS DECRETOS QUE INDICA. MINISTERIO DE ECONOMÍA, FOMENTO Y TURISMO; SUBSECRETARÍA DE ECONOMÍA Y EMPRESAS DE MENOR TAMAÑO | N9: https://digital.gob.cl/biblioteca/regulacion/
A10: Decreto MINECON 2019-24 | B10: =if(A10="","", countif(Obligaciones!$D$3:$D$20388,A10)) -> 35 | C10: Norma técnica | D10: Complementa a | E10: Ley 19799 | F10: https://bcn.cl/2gwjg | G10: Ministerio de Economía, Fomento y Reconstrucción | H10: Sobre documentos electrónicos, firma electrónica y servicios de certificación de dicha firma | I10: 43564 | J10: 45064 | K10: DECRETO 24 APRUEBA NORMA TÉCNICA PARA LA PRESTACIÓN DEL SERVICIO DE CERTIFICACIÓN DE FIRMA ELECTRÓNICA AVANZADA. MINISTERIO DE ECONOMÍA, FOMENTO Y TURISMO; SUBSECRETARÍA DE ECONOMÍA Y EMPRESAS DE MENOR TAMAÑO | L10: Fecha de publicación: v.Año: 2019 | M10: Aprueba norma técnica para la prestación de servicios de... | N10: https://digital.gob.cl/biblioteca/regulacion/
A11: Decreto MINSEGPRES 2015-1 | B11: =if(A11="","", countif(Obligaciones!$D$3:$D$20388,A11)) -> 92 | C11: Norma técnica | D11: Complementa a | E11: Ley 19799 | F11: https://bcn.cl/2m5gb | G11: Ministerio Secretaría General de la Presidencia | H11: Sobre sistemas y sitios web de los órganos de la administración del Estado | I11: 42166 | J11: 45064 | K11: DECRETO 1 APRUEBA NORMA TÉCNICA SOBRE SISTEMAS Y SITIOS WEB DE LOS ÓRGANOS DE LA ADMINISTRACIÓN DEL ESTADO. MINISTERIO SECRETARÍA GENERAL DE LA PRESIDENCIA | L11: Fecha de publicación: v.Año: 2015 | M11: Aprueba norma técnica sobre sistemas y sitios web de los órganos de la... | N11: https://digital.gob.cl/biblioteca/regulacion/
A12: Decreto MINSEGPRES 2006-93 | B12: =if(A12="","", countif(Obligaciones!$D$3:$D$20388,A12)) -> 0 | C12: Norma técnica | D12: Complementa a | E12: Ley 19799 | F12: https://bcn.cl/2o11a | G12: Ministerio Secretaría General de la Presidencia | H12: Sobre mensajes no deseados recibidos por el Estado y sus funcionarios/as | I12: 38926 | J12: 45064 | K12: DECRETO 93 APRUEBA NORMA TECNICA PARA LA ADOPCION DE MEDIDAS DESTINADAS A MINIMIZAR LOS EFECTOS PERJUDICIALES DE LOS MENSAJES ELECTRONICOS MASIVOS NO SOLICITADOS RECIBIDOS EN LAS CASILLAS ELECTRONICAS DE LOS ORGANOS DE LA ADMINISTRACION DEL ESTADO Y DE SUS FUNCIONARIOS. MINISTERIO SECRETARÍA GENERAL DE LA PRESIDENCIA | L12: Fecha de publicación: v.Año: 2006 | M12: Aprueba norma técnica para la adopción de medidas destinadas a minimizar... | N12: https://digital.gob.cl/biblioteca/regulacion/
A13: Decreto MINSEGPRES 2005-83 | B13: =if(A13="","", countif(Obligaciones!$D$3:$D$20388,A13)) -> 0 | C13: Norma técnica | D13: Complementa a | E13: Ley 19799 | F13: https://bcn.cl/2kdhg | G13: Ministerio Secretaría General de la Presidencia | H13: Sobre seguridad y confidencialidad de los documentos electrónicos | I13: 38364 | J13: 45064 | K13: DECRETO 83 APRUEBA NORMA TECNICA PARA LOS ORGANOS DE LA ADMINISTRACION DEL ESTADO SOBRE SEGURIDAD Y CONFIDENCIALIDAD DE LOS DOCUMENTOS ELECTRONICOS. MINISTERIO SECRETARÍA GENERAL DE LA PRESIDENCIA | L13: Fecha de publicación: v.Año: 2005 | M13: Aprueba norma técnica para los órganos de la administración del Estado sobre... | N13: https://digital.gob.cl/biblioteca/regulacion/
B14: =if(A14="","", countif(Obligaciones!$D$3:$D$20388,A14))
A15: Ley 18993 | B15: =if(A15="","", countif(Obligaciones!$D$3:$D$20388,A15)) -> 0 | C15: Ley | D15: Original | F15: https://bcn.cl/3cxwf | G15: Ministerio del Interior | H15: Sobre la institucionalidad de la División de Gobierno Digital | I15: 33106 | J15: 45064 | K15: LEY 18993 CREA MINISTERIO SECRETARIA GENERAL DE LA PRESIDENCIA DE LA REPUBLICA. MINISTERIO DEL INTERIOR
A16: Ley 21050 | B16: =if(A16="","", countif(Obligaciones!$D$3:$D$20388,A16)) -> 0 | C16: Ley | D16: Original | F16: https://bcn.cl/2kam1 | G16: Ministerio de Hacienda | H16: Sobre la institucionalidad de la División de Gobierno Digital | I16: 43076 | J16: 45064 | K16: Ley Nº 21.050: Otorga reajuste de remuneraciones a los trabajadores del sector público, concede aguinaldos que señala, concede otros beneficios que indica y modifica diversos cuerpos legales. | L16: Fecha de publicación: v.Año: 2017 | M16: Ley que modifica la ley N° 18.993 que crea Ministerio Secretaría General de... | N16: https://digital.gob.cl/biblioteca/regulacion/
A17: Ley 21045 | B17: =if(A17="","", countif(Obligaciones!$D$3:$D$20388,A17)) -> 507 | C17: Ley | D17: Original | F17: https://bcn.cl/2f7iu | G17: Ministerio de Educación | H17: Sobre la institucionalidad del Archivo Nacional | I17: 43042 | J17: 45064 | K17: LEY 21045 Firma electrónica CREA EL MINISTERIO DE LAS CULTURAS, LAS ARTES Y EL PATRIMONIO. MINISTERIO DE EDUCACIÓN
A18: DFL MINEDUC 1929-5200 | B18: =if(A18="","", countif(Obligaciones!$D$3:$D$20388,A18)) -> 130 | C18: Decreto con Fuerza de Ley | D18: Original | F18: https://bcn.cl/2fa2y | G18: Ministerio de Educación | H18: Sobre la institucionalidad del Archivo Nacional | I18: 10937 | J18: 45064 | K18: DFL 5200 SOBRE INSTITUCIONES NACIONALES PATRIMONIALES DEPENDIENTES DEL SERVICIO NACIONAL DEL PATRIMONIO CULTURAL. MINISTERIO DE EDUCACIÓN PÚBLICA
A19: Decreto MINSEGPRES 2018-12 | B19: =if(A19="","", countif(Obligaciones!$D$3:$D$20388,A19)) -> 0 | C19: Decreto | D19: Original | F19: https://bcn.cl/2rlya | G19: Ministerio Secretaría General de la Presidencia | H19: Sobre la institucionalidad del Consejo Asesor Permanente para la Modernización del Estado y la Secretaría de Modernización del Estado | I19: 43461 | J19: 45064 | K19: DECRETO 12 CREA "CONSEJO ASESOR PERMANENTE PARA LA MODERNIZACIÓN DEL ESTADO" Y ORGANIZA LA "SECRETARÍA DE MODERNIZACIÓN DEL ESTADO". MINISTERIO SECRETARÍA GENERAL DE LA PRESIDENCIA
A20: Decreto MINSEGPRES 2021-5 | B20: =if(A20="","", countif(Obligaciones!$D$3:$D$20388,A20)) -> 0 | C20: Decreto | D20: Modifica a | E20: Decreto MINSEGPRES 2018-12 | F20: https://bcn.cl/3cxwo | G20: Ministerio Secretaría General de la Presidencia | H20: Sobre la institucionalidad del Consejo Asesor Permanente para la Modernización del Estado y la Secretaría de Modernización del Estado | I20: 44411 | J20: 45064 | K20: DECRETO 5 MODIFICA DECRETO SUPREMO N° 12, DE 25 DE JUNIO DE 2018, DEL MINISTERIO SECRETARÍA GENERAL DE LA PRESIDENCIA, EN EL SENTIDO QUE SE SEÑALA, Y RENUEVA Y DESIGNA MIEMBROS QUE INDICA DEL CONSEJO ASESOR PERMANENTE PARA LA MODERNIZACIÓN DEL ESTADO. MINISTERIO SECRETARÍA GENERAL DE LA PRESIDENCIA
A21: Decreto MINSEGPRES 2022-19 | B21: =if(A21="","", countif(Obligaciones!$D$3:$D$20388,A21)) -> 0 | C21: Decreto | D21: Modifica a | E21: Decreto MINSEGPRES 2018-12 | F21: https://bcn.cl/3cxwp | G21: Ministerio Secretaría General de la Presidencia | H21: Sobre la institucionalidad del Consejo Asesor Permanente para la Modernización del Estado y la Secretaría de Modernización del Estado | I21: 44901 | J21: 45064 | K21: DECRETO 19 MODIFICA DECRETO SUPREMO Nº 12, DE 25 DE JUNIO DE 2018, DEL MINISTERIO SECRETARÍA GENERAL DE LA PRESIDENCIA, EN EL SENTIDO QUE SE SEÑALA, Y RENUEVA Y DESIGNA MIEMBROS QUE INDICA DEL CONSEJO ASESOR PERMANENTE PARA LA MODERNIZACIÓN DEL ESTADO. MINISTERIO SECRETARÍA GENERAL DE LA PRESIDENCIA
A22: Decreto MINECON 2015-44 | B22: =if(A22="","", countif(Obligaciones!$D$3:$D$20388,A22)) -> 0 | C22: Decreto | D22: Original | F22: https://bcn.cl/3cxwq | G22: Ministerio de Economía, Fomento y Reconstrucción | H22: Sobre la institucionalidad del laboratorio de gobierno | I22: 42132 | J22: 45064 | K22: RESOLUCIÓN 44 AFECTA EJECUTA ACUERDO DE CONSEJO Nº 2.867, DE 2015, Y MODIFICA RESOLUCIÓN (A) Nº 50, DE 2014, MODIFICADA POR RESOLUCIONES (A) Nº 7 Y Nº 20, AMBAS DE 2015 Y DE CORFO, QUE APROBÓ EL REGLAMENTO POR EL QUE SE RIGE EL "COMITÉ DE INNOVACIÓN EN EL SECTOR PÚBLICO". MINISTERIO DE ECONOMÍA, FOMENTO Y TURISMO; CORPORACIÓN DE FOMENTO DE LA PRODUCCIÓN
A23: Decreto MINECON 2018-100 | B23: =if(A23="","", countif(Obligaciones!$D$3:$D$20388,A23)) -> 0 | C23: Decreto | D23: Deroga a | F23: https://bcn.cl/3cxwr | G23: Ministerio de Economía, Fomento y Reconstrucción | H23: Sobre la institucionalidad del laboratorio de gobierno | I23: 43404 | J23: 45064 | K23: RESOLUCIÓN 100 EJECUTA ACUERDO DE CONSEJO Nº 2.997, DE 2018, QUE DEJA SIN EFECTO ACUERDOS DE CONSEJO Nº 2.826, DE 2014; Nº 2.859, Nº 2.867 Y Nº 2.895, TODOS DE 2015; Nº 2.924 Y Nº 2.940, AMBOS DE 2016; Y Nº 2.956, DE 2017; CREA EL "COMITÉ DE INNOVACIÓN EN EL SECTOR PÚBLICO"; Y APRUEBA REGLAMENTO DEL COMITÉ. MINISTERIO DE ECONOMÍA, FOMENTO Y TURISMO; CORPORACIÓN DE FOMENTO DE LA PRODUCCIÓN
A24: Decreto MINECON 2020-1314 | B24: =if(A24="","", countif(Obligaciones!$D$3:$D$20388,A24)) -> 0 | C24: Decreto | D24: Pone término | F24: https://bcn.cl/3cxws | G24: Ministerio de Economía, Fomento y Reconstrucción | H24: Sobre la institucionalidad del laboratorio de gobierno | I24: 44187 | J24: 45064 | K24: RESOLUCIÓN 1314 EXENTA EJECUTA ACUERDO DE CONSEJO Nº 3.092, DE 2020, QUE "DEJA SIN EFECTO ACUERDOS DE CONSEJO Nº 2.997, DE 2018 Y Nº 3.031, DE 2019; Y PONE TÉRMINO AL "COMITÉ DE INNOVACIÓN EN EL SECTOR PÚBLICO" MINISTERIO DE ECONOMÍA, FOMENTO Y TURISMO; CORPORACIÓN DE FOMENTO DE LA PRODUCCIÓN
B25: =if(A25="","", countif(Obligaciones!$D$3:$D$20388,A25))
A26: DS MININTERIOR 1999-5996 | B26: =if(A26="","", countif(Obligaciones!$D$3:$D$20388,A26)) -> 0 | C26: Decreto Supremo | D26: Original | F26: https://bcn.cl/2xo8i | G26: Ministerio del Interior | H26: Sobre la red interna (Intranet) del Estado | I26: 36476 | J26: 45064 | K26: Decreto Supremo N°5996, de 1999: Crea Red Interna (INTRANET) del Estado y entrega su implementación, puesta en marcha, administración, coordinación y supervisión al Ministerio del Interior y Seguridad Pública. | N26: CSIRT
A27: DS MININTERIOR 2005-1299 | B27: =if(A27="","", countif(Obligaciones!$D$3:$D$20388,A27)) -> 0 | C27: Decreto Supremo | D27: Complementa a | E27: DS MININTERIOR 1999-5996 | F27: https://bcn.cl/3cy8w | G27: Ministerio del Interior | H27: Sobre la red interna (Intranet) del Estado | I27: 38471 | J27: 45064 | K27: DECRETO 1299 ESTABLECE NUEVAS NORMAS QUE REGULAN LA RED DE CONECTIVIDAD DEL ESTADO QUE ADMINISTRA EL MINISTERIO DEL INTERIOR Y FIJA LOS PROCEDIMIENTOS, REQUISITOS Y ESTANDARES TECNOLOGICOS PARA LA INCORPORACION A DICHA RED DE INSTITUCIONES PUBLICAS. MINISTERIO DEL INTERIOR; SUBSECRETARIA DEL INTERIOR | N27: CSIRT
A28: Decreto MTT 2003-5 | B28: =if(A28="","", countif(Obligaciones!$D$3:$D$20388,A28)) -> 0 | C28: Decreto Supremo | D28: Original | F28: https://bcn.cl/2kfik | G28: Ministerio de Transportes y Telecomunicaciones | H28: Sobre la institucionalidad del Consejo nacional de nombres de dominio y números IP | I28: 37796 | J28: 45064 | K28: DECRETO 5 CREA CONSEJO NACIONAL DE NOMBRES DE DOMINIO Y NUMEROS IP. MINISTERIO DE TRANSPORTES Y TELECOMUNICACIONES; SUBSECRETARIA DE TELECOMUNICACIONES
B29: =if(A29="","", countif(Obligaciones!$D$3:$D$20388,A29))
A30: Ley 18845 | B30: =if(A30="","", countif(Obligaciones!$D$3:$D$20388,A30)) -> 64 | C30: Ley | D30: Modificada por | E30: Ley 21180 | F30: https://bcn.cl/2li93 | G30: Ministerio de Justicia | H30: Sobre sistemas de microcopia o micrograbación de documentos | I30: 32815 | J30: 45064 | K30: LEY 18845 ESTABLECE SISTEMAS DE MICROCOPIA O MICROGRABACION DE DOCUMENTOS. MINISTERIO DE JUSTICIA
A31: Ley 19880 | B31: =if(A31="","", countif(Obligaciones!$D$3:$D$20388,A31)) -> 350 | C31: Ley | D31: Modificada por | E31: Ley 21180 | F31: https://bcn.cl/2f82ee | G31: Ministerio Secretaría General de la Presidencia | H31: Sobre los procedimientos administrativos | I31: 37770 | J31: 45064 | K31: LEY Nº 19880 ESTABLECE BASES DE LOS PROCEDIMIENTOS ADMINISTRATIVOS QUE RIGEN LOS ACTOS DE LOS ORGANOS DE LA ADMINISTRACION DEL ESTADO.. MINISTERIO SECRETARÍA GENERAL DE LA PRESIDENCIA | L31: Fecha de publicación: v.Año: 2003 | M31: Establece la forma en que las instituciones del Estado deben llevar a... | N31: https://digital.gob.cl/biblioteca/regulacion/
A32: Ley 20766 | B32: =if(A32="","", countif(Obligaciones!$D$3:$D$20388,A32)) -> 53 | C32: Ley | D32: Modificada por | E32: Ley 21180 | F32: https://bcn.cl/2pk6k | G32: Ministerio Secretaría General de la Presidencia | H32: Sobre el procedimiento de toma de razón y registros electrónicos | I32: 41843 | J32: 45064 | K32: LEY 20766 Firma electrónica PROCEDIMIENTO DE TOMA DE RAZÓN Y REGISTRO ELECTRÓNICOS. MINISTERIO SECRETARÍA GENERAL DE LA PRESIDENCIA
A34: Ley 21180 | B34: =if(A34="","", countif(Obligaciones!$D$3:$D$20388,A34)) -> 192 | C34: Ley | D34: Original | F34: https://bcn.cl/3cxwe | G34: Ministerio Secretaría General de la Presidencia | H34: Sobre la transformación digital del Estado | I34: 43780 | J34: 45064 | K34: Ley Nº21.180 sobre Transformación Digital del Estado | L34: Fecha de publicación: v.Año: 2019 | M34: Ley que modifica la ley Nº19.880 que establece las bases para los... | N34: https://digital.gob.cl/biblioteca/regulacion/
A35: Ley 21464 | B35: =if(A35="","", countif(Obligaciones!$D$3:$D$20388,A35)) -> 68 | C35: Ley | D35: Modifica a | E35: Ley 21180 | F35: https://bcn.cl/32hvm | G35: Ministerio Secretaría General de la Presidencia | H35: Sobre la transformación digital del Estado | I35: 44721 | J35: 45064 | K35: Ley Nº 21.464 MODIFICA DIVERSOS CUERPOS LEGALES, EN MATERIA DE TRANSFORMACIÓN DIGITAL DEL ESTADO MINISTERIO SECRETARÍA GENERAL DE LA PRESIDENCIA | L35: Fecha de publicación: v.1 | M35: Modifica diversos cuerpos legales en materia de Transformación Digital del... | N35: https://digital.gob.cl/biblioteca/regulacion/
A36: DFL MINSEGPRES 2021-1 | B36: =if(A36="","", countif(Obligaciones!$D$3:$D$20388,A36)) -> 0 | C36: Decreto con Fuerza de Ley | D36: Complementa a | E36: Ley 21180 | F36: https://bcn.cl/2obw9 | G36: Ministerio Secretaría General de la Presidencia | H36: Sobre la gradualidad | I36: 44292 | J36: 45064 | K36: Decreto de gradualidad de la Ley de Transformación Digital 21.180 | L36: Fecha de publicación: v.1, Abril 2021 | M36: Decreto sobre gradualidad de implementación de la Ley de... | N36: https://digital.gob.cl/biblioteca/regulacion/
A37: Decreto MINSEGPRES 2021-4 | B37: =if(A37="","", countif(Obligaciones!$D$3:$D$20388,A37)) -> 0 | C37: Reglamento | D37: Complementa a | E37: Ley 21180 | F37: https://bcn.cl/2uejl | G37: Ministerio Secretaría General de la Presidencia | H37: Sobre los procedimientos administrativos | I37: 44541 | J37: 45064 | K37: Ley de Transformación Digital. Decreto N° 4 | Reglamento. // DECRETO 4 REGLAMENTO QUE REGULA LA FORMA EN QUE LOS PROCEDIMIENTOS ADMINISTRATIVOS DEBERÁN EXPRESARSE A TRAVÉS DE MEDIOS ELECTRÓNICOS, EN LAS MATERIAS QUE INDICA, SEGÚN LO DISPUESTO EN LA LEY Nº 21.180 SOBRE TRANSFORMACIÓN DIGITAL DEL ESTADO. MINISTERIO SECRETARÍA GENERAL DE LA PRESIDENCIA | L37: Fecha de publicación: v.1 | M37: Decreto que regula la forma en que los procedimientos administrativos... | N37: https://digital.gob.cl/biblioteca/regulacion/
A38: DFL MINCULTURAS 2021-1 | B38: =if(A38="","", countif(Obligaciones!$D$3:$D$20388,A38)) -> 0 | C38: Decreto con Fuerza de Ley | D38: Complementa a | E38: Ley 21180 | F38: https://bcn.cl/2o2as | G38: Ministerio de las Culturas, las Artes y el Patrimonio | H38: Sobre las microformas | I38: 44270 | J38: 45064 | K38: DFL 1 DETERMINA LOS REQUISITOS DEL MÉTODO DE ELABORACIÓN, CONSERVACIÓN Y USO DE LAS MICROFORMAS Y DE AQUELLOS A EMPLEAR EN LA DESTRUCCIÓN DE DOCUMENTOS ORIGINALES EN VIRTUD DE LA LEY N° 18.845. MINISTERIO DE LAS CULTURAS, LAS ARTES Y EL PATRIMONIO
A39: Decreto MINCULTURAS 2021-23 | B39: =if(A39="","", countif(Obligaciones!$D$3:$D$20388,A39)) -> 74 | C39: Reglamento | D39: Complementa a | E39: Ley 21180 | F39: https://bcn.cl/2t7yl | G39: Ministerio de las Culturas, las Artes y el Patrimonio | H39: Sobre las microformas | I39: 44490 | J39: 45064 | K39: Ley de Transformación Digital. Decreto N° 23 | Reglamento. // DECRETO 23 APRUEBA EL REGLAMENTO QUE ESTABLECE LOS MEDIOS Y PROCEDIMIENTOS TÉCNICOS Y ADMINISTRATIVOS QUE SE UTILIZARÁN EN LA GENERACIÓN DE MICROFORMAS. MINISTERIO DE LAS CULTURAS, LAS ARTES Y EL PATRIMONIO; SUBSECRETARÍA DEL PATRIMONIO CULTURAL | L39: Fecha de publicación: v.1 | M39: Decreto que establece los medios y procedimientos técnicos y... | N39: https://digital.gob.cl/biblioteca/regulacion/
A40: Decreto MINCULTURAS 2021-24 | B40: =if(A40="","", countif(Obligaciones!$D$3:$D$20388,A40)) -> 0 | C40: Reglamento | D40: Complementa a | E40: Ley 21180 | F40: https://bcn.cl/2vn1a | G40: Ministerio de las Culturas, las Artes y el Patrimonio | H40: Sobre el archivo electrónico del Archivo Nacional | I40: 44490 | J40: 45064 | K40: Ley de Transformación Digital.. Decreto N° 24 | Reglamento. //DECRETO 24 REGLAMENTO QUE ESTABLECE LOS ESTÁNDARES TÉCNICOS Y ADMINISTRATIVOS DEL ARCHIVO ELECTRÓNICO DESARROLLADO POR EL ARCHIVO NACIONAL. MINISTERIO DE LAS CULTURAS, LAS ARTES Y EL PATRIMONIO; SUBSECRETARÍA DEL PATRIMONIO CULTURAL | L40: Fecha de publicación: v.1 | M40: Decreto sobre los estándares técnicos y administrativos del archivo electrónico... | N40: https://digital.gob.cl/biblioteca/regulacion/
A42: Ley 18290 | F42: https://bcn.cl/2lcu2
A43: DFL MTT 2009-1 | B43: =if(A43="","", countif(Obligaciones!$D$3:$D$20388,A43)) -> 2488 | C43: Decreto con Fuerza de Ley | D43: Original | F43: https://bcn.cl/32g67 | G43: Ministerio de Transportes y Telecomunicaciones | H43: Sobre la ley de tránsito | I43: 40115 | J43: 45064 | K43: DFL 1 FIJA TEXTO REFUNDIDO, COORDINADO Y SISTEMATIZADO DE LA LEY DE TRÁNSITO. MINISTERIO DE TRANSPORTES Y TELECOMUNICACIONES; SUBSECRETARÍA DE TRANSPORTES; MINISTERIO DE JUSTICIA; SUBSECRETARÍA DE JUSTICIA
B44: =if(A44="","", countif(Obligaciones!$D$3:$D$20388,A44))
A45: Instructivo Presidencial 2019-1 | B45: =if(A45="","", countif(Obligaciones!$D$3:$D$20388,A45)) -> 0 | C45: Instructivo Presidencial | D45: Original | F45: https://digital.gob.cl/biblioteca/regulacion/instructivo-presidencial-no1-transformacion-digital/ | G45: Presidencia de la República | H45: Sobre la transformación digital del Estado | I45: 43477 | J45: 45064 | K45: Instructivo Presidencial Nº1 Transformación Digital | L45: Fecha de publicación: v.Año: 2019 | M45: Imparte instrucciones sobre Transformación digital en los órganos... | N45: https://digital.gob.cl/biblioteca/regulacion/
A46: Instructivo Presidencial 2019-4 | B46: =if(A46="","", countif(Obligaciones!$D$3:$D$20388,A46)) -> 0 | C46: Instructivo Presidencial | D46: Original | F46: https://digital.gob.cl/biblioteca/regulacion/instructivo-presidencial-no4-simplificacion-regulatoria-y-legislativa/ | G46: Presidencia de la República | H46: Sobre la simplificación regulatoria y legislativa | I46: 43477 | J46: 45064 | K46: Instructivo Presidencial Nº4: Simplificación regulatoria y legislativa. | L46: Fecha de publicación: v.Año: 2019 | M46: Imparte instrucciones sobre medidas de simplificación legislativa y regulatoria. | N46: https://digital.gob.cl/biblioteca/regulacion/
A47: Instructivo Presidencial 2018-8 | B47: =if(A47="","", countif(Obligaciones!$D$3:$D$20388,A47)) -> 0 | C47: Instructivo Presidencial | D47: Original | F47: https://digital.gob.cl/biblioteca/regulacion/instructivo-presidencial-no8-ciberseguridad/ | G47: Presidencia de la República | H47: Sobre ciberseguridad | I47: 43112 | J47: 45064 | K47: Instructivo Presidencial Nº8: Ciberseguridad | L47: Fecha de publicación: v.Año: 2018 | M47: Imparte instrucciones urgentes en materia de ciberseguridad a los... | N47: https://digital.gob.cl/biblioteca/regulacion/
A48: Instructivo Presidencial 2018-1 | B48: =if(A48="","", countif(Obligaciones!$D$3:$D$20388,A48)) -> 0 | C48: Instructivo Presidencial | D48: Original | F48: https://digital.gob.cl/biblioteca/regulacion/instructivo-presidencial-no1-uso-de-servicios-de-la-nube/ | G48: Presidencia de la República | H48: Sobre servicios en la nube | I48: 43112 | J48: 45064 | K48: Instructivo Presidencial Nº1: Uso de servicios de la Nube | L48: Fecha de publicación: v.Año: 2018 | M48: Imparte instrucciones sobre uso de servicios en la nube a los órganos de... | N48: https://digital.gob.cl/biblioteca/regulacion/
A49: Instructivo Presidencial 2012-2 | B49: =if(A49="","", countif(Obligaciones!$D$3:$D$20388,A49)) -> 69 | C49: Instructivo Presidencial | D49: Original | F49: https://digital.gob.cl/biblioteca/regulacion/instructivo-presidencial-no2-chile-sin-papeleo/ | G49: Presidencia de la República | H49: Sobre los procedimientos administrativos | I49: 41138 | J49: 45064 | K49: Instructivo Presidencial Nº2: Chile sin papeleo | L49: Fecha de publicación: v.Año: 2012 | M49: Imparte instrucciones sobre simplificación de trámites y... | N49: https://digital.gob.cl/biblioteca/regulacion/
A50: Instructivo Presidencial 2012-5 | B50: =if(A50="","", countif(Obligaciones!$D$3:$D$20388,A50)) -> 0 | C50: Instructivo Presidencial | D50: Original | F50: https://digital.gob.cl/biblioteca/regulacion/instructivo-presidencial-no5-gobierno-abierto/ | G50: Presidencia de la República | H50: Sobre gobierno abierto | I50: 40920 | J50: 45064 | K50: Instructivo Presidencial Nº5: Gobierno Abierto | L50: Fecha de publicación: v.Año: 2012 | M50: Imparte instrucciones sobre Gobierno Abierto. | N50: https://digital.gob.cl/biblioteca/regulacion/
B51: =if(A51="","", countif(Obligaciones!$D$3:$D$20388,A51))
A52: Norma Técnica de Documentos y expedientes electrónicos 2022-3 | B52: =if(A52="","", countif(Obligaciones!$D$3:$D$20388,A52)) -> 543 | C52: Norma técnica | D52: Consulta pública | F52: https://digital.gob.cl/biblioteca/regulacion/documento-tercera-consulta-publica-ley-21180-norma-tecnica-de-documentos-y-expedientes/ | G52: Ministerio Secretaría General de la Presidencia | H52: Sobre documentos y expedientes electrónicos | I52: 44568 | J52: 45064 | K52: Documento Tercera Consulta Pública Ley 21.180 - Norma Técnica de Documentos y Expedientes. | L52: Fecha de publicación: v.1 | M52: Documento sobre los contenidos técnicos propuestos para la Norma... | N52: https://digital.gob.cl/biblioteca/regulacion/
A53: Norma Técnica de Seguridad de la información y ciberseguridad 2021-3 | B53: =if(A53="","", countif(Obligaciones!$D$3:$D$20388,A53)) -> 545 | C53: Norma técnica | D53: Consulta pública | F53: https://digital.gob.cl/biblioteca/regulacion/documento-tercera-consulta-publica-ley-21180-norma-tecnica-de-seguridad-de-la-informacion-y-ciberseguridad/ | G53: Ministerio Secretaría General de la Presidencia | H53: Sobre seguridad de la Información y ciberseguridad | I53: 44546 | J53: 45064 | K53: Documento Tercera Consulta Pública Ley 21.180 - Norma Técnica de Seguridad de la Información y Ciberseguridad. | L53: Fecha de publicación: v.1 | M53: Documento sobre los contenidos técnicos propuestos para la Norma... | N53: https://digital.gob.cl/biblioteca/regulacion/
A54: Norma Técnica de Notificaciones 2021-3 | B54: =if(A54="","", countif(Obligaciones!$D$3:$D$20388,A54)) -> 648 | C54: Norma técnica | D54: Consulta pública | F54: https://digital.gob.cl/biblioteca/regulacion/documento-tercera-consulta-publica-ley-21180-norma-tecnica-de-notificaciones/ | G54: Ministerio Secretaría General de la Presidencia | H54: Sobre las notificaciones | I54: 44546 | J54: 45064 | K54: Documento Tercera Consulta Pública Ley 21.180 - Norma Técnica de Notificaciones. | L54: Fecha de publicación: v.1 | M54: Documento sobre los contenidos técnicos propuestos para la Norma... | N54: https://digital.gob.cl/biblioteca/regulacion/
A55: Norma Técnica de Interoperabilidad 2021-3 | B55: =if(A55="","", countif(Obligaciones!$D$3:$D$20388,A55)) -> 600 | C55: Norma técnica | D55: Consulta pública | F55: https://digital.gob.cl/biblioteca/regulacion/tercera-consulta-publica-ley-n-21180-de-transformacion-digital-del-estado-norma-tecnica-de-interoperabilidad/ | G55: Ministerio Secretaría General de la Presidencia | H55: Sobre interoperabilidad | I55: 44546 | J55: 45064 | K55: Tercera consulta pública Ley N° 21.180, de Transformación Digital del Estado. Norma Técnica de Interoperabilidad. | L55: Fecha de publicación: v.1 | M55: Documento sobre los contenidos técnicos propuestos para la Norma... | N55: https://digital.gob.cl/biblioteca/regulacion/
A56: Norma Técnica de Calidad y funcionamiento 2021-3 | B56: =if(A56="","", countif(Obligaciones!$D$3:$D$20388,A56)) -> 570 | C56: Norma técnica | D56: Consulta pública | F56: https://digital.gob.cl/biblioteca/regulacion/ley-n-21180-de-transformacion-digital-estado/ | G56: Ministerio Secretaría General de la Presidencia | H56: Sobre calidad y funcionamiento de las plataformas electrónicas | I56: 44428 | J56: 45064 | K56: Informe tercera consulta pública Ley N° 21.180, de Transformación Digital del Estado: Norma Técnica de Calidad y Funcionamiento. | L56: Fecha de publicación: v.1 | M56: Informe tercera consulta pública Ley N° 21.180, de Transformación Digital del... | N56: https://digital.gob.cl/biblioteca/regulacion/
A57: Norma Técnica de Autenticación 2021-3 | B57: =if(A57="","", countif(Obligaciones!$D$3:$D$20388,A57)) -> 288 | C57: Norma técnica | D57: Consulta pública | F57: https://digital.gob.cl/biblioteca/regulacion/documento-tercera-consulta-publica-ley-21180-norma-tecnica-de-autenticacion/ | G57: Ministerio Secretaría General de la Presidencia | H57: Sobre la autenticación | I57: 44460 | J57: 45064 | K57: Documento Tercera Consulta Pública Ley 21.180 - Norma Técnica de Autenticación
A59: Norma Técnica de Seguridad de la información y ciberseguridad Decreto MINSEGPRES 2023-7 | B59: =if(A59="","", countif(Obligaciones!$D$3:$D$20388,A59)) -> 165 | C59: Norma técnica | D59: Original | F59: https://bcn.cl/3enj9 | G59: Ministerio Secretaría General de la Presidencia | H59: Sobre seguridad de la Información y ciberseguridad | I59: 45155 | J59: 45157 | K59: DECRETO 7 ESTABLECE NORMA TÉCNICA DE SEGURIDAD DE LA INFORMACIÓN Y CIBERSEGURIDAD CONFORME LA LEY Nº 21.180 MINISTERIO SECRETARÍA GENERAL DE LA PRESIDENCIA
A60: Norma Técnica de Interoperabilidad 2023-12 | B60: =if(A60="","", countif(Obligaciones!$D$3:$D$20388,A60)) -> 296 | C60: Norma técnica | D60: Original | F60: https://bcn.cl/3enmo | G60: Ministerio Secretaría General de la Presidencia | H60: Sobre interoperabilidad | I60: 45155 | J60: 45160 | K60: DECRETO 12 ESTABLECE NORMA TÉCNICA DE INTEROPERABILIDAD. MINISTERIO SECRETARÍA GENERAL DE LA PRESIDENCIA
B65: =if(A65="","", countif(Obligaciones!$D$3:$D$20388,A65))
A66: Ley 19628 | B66: =if(A66="","", countif(Obligaciones!$D$3:$D$20388,A66)) -> 0 | C66: Ley | D66: Original | F66: https://bcn.cl/2f7cg | G66: Ministerio Secretaría General de la Presidencia | H66: Sobre protección de la vida privada | I66: 36400 | J66: 45064 | K66: Ley N° 19.628, sobre Protección de la Vida Privada; | L66: Fecha de publicación: v.Año: 1998 | M66: Define los datos personales y sensibles que deben ser resguardados para... | N66: https://digital.gob.cl/biblioteca/regulacion/
B67: =if(A67="","", countif(Obligaciones!$D$3:$D$20388,A67))
A68: Ley 17336 | B68: =if(A68="","", countif(Obligaciones!$D$3:$D$20388,A68)) -> 0 | C68: Ley | D68: Original | F68: https://bcn.cl/2f6sl | G68: Ministerio de Educación | H68: Sobre propiedad intelectual y derecho de autor | I68: 25843 | J68: 45064 | K68: Ley N° 17.336 de Propiedad Intelectual, Derecho de Autor | L68: Fecha de publicación: v.Año: 1970 | M68: Ley que protege los derechos que, por el solo hecho de la creación de la obra,... | N68: https://digital.gob.cl/biblioteca/regulacion/
A69: Ley 19039 | B69: =if(A69="","", countif(Obligaciones!$D$3:$D$20388,A69)) -> 0 | C69: Ley | F69: https://bcn.cl/2l1dx | G69: Ministerio de Economía, Fomento y Reconstrucción | H69: Sobre propiedad intelectual y derecho de autor | I69: 33263 | J69: 45064 | K69: Ley N° 17.336 y N°19.039, sobre Propiedad Intelectual; | N69: www.mercadopublico.cl | O69: El proveedor por el sólo hecho de participar en este proceso se someterá a la legislación chilena y, entre otros, a los siguientes cuerpos legales y reglamentos, así como sus eventuales modificaciones:
A70: Ley 19996 | B70: =if(A70="","", countif(Obligaciones!$D$3:$D$20388,A70)) -> 0 | C70: Ley | D70: Modifica a | E70: Ley 19039 | F70: https://bcn.cl/2pp3f | G70: Ministerio de Economía, Fomento y Reconstrucción | H70: Sobre propiedad intelectual y derecho de autor | I70: 38422 | J70: 45064 | K70: LEY 19996 MODIFICA LA LEY Nº 19.039, SOBRE PROPIEDAD INDUSTRIAL MINISTERIO DE ECONOMÍA; FOMENTO Y RECONSTRUCCION; SUBSECRETARIA DE ECONOMIA; FOMENTO Y RECONSTRUCCION
A71: DFL MINECON 2022-4 | B71: =if(A71="","", countif(Obligaciones!$D$3:$D$20388,A71)) -> 0 | C71: DFL | F71: https://bcn.cl/34hx8 | G71: Ministerio de Economía, Fomento y Reconstrucción | H71: Sobre propiedad intelectual y derecho de autor | I71: 44779 | J71: 45064 | K71: DFL 4 FIJA TEXTO REFUNDIDO, COORDINADO Y SISTEMATIZADO DE LA LEY N° 19.039, DE PROPIEDAD INDUSTRIAL. MINISTERIO DE ECONOMÍA, FOMENTO Y TURISMO; SUBSECRETARÍA DE ECONOMÍA Y EMPRESAS DE MENOR TAMAÑO
B72: =if(A72="","", countif(Obligaciones!$D$3:$D$20388,A72))
A73: Ley 20730 | B73: =if(A73="","", countif(Obligaciones!$D$3:$D$20388,A73)) -> 0 | C73: Ley | D73: Original | F73: https://bcn.cl/2f8jc | G73: Ministerio Secretaría General de la Presidencia | H73: Sobre el lobby y las gestiones que representen intereses particulares | I73: 41706 | J73: 45064 | K73: Ley Nº 20.730: Regula el lobby y las gestiones que representen intereses particulares | L73: Fecha de publicación: v.Año: 2014 | M73: Regula el lobby y las gestiones que representen intereses particulares ante... | N73: https://digital.gob.cl/biblioteca/regulacion/
A74: Ley 20478 | B74: =if(A74="","", countif(Obligaciones!$D$3:$D$20388,A74)) -> 0 | C74: Ley | D74: Original | F74: https://bcn.cl/2fcje | G74: Ministerio de Transportes y Telecomunicaciones | H74: Sobre recuperación y continuidad en condiciones críticas y de emergencia del sistema público de telecomunicaciones | I74: 40522 | J74: 45064 | K74: Ley N° 20.478, Sobre recuperación y continuidad en condiciones críticas y de emergencia del sistema público de telecomunicaciones | L74: Fecha de publicación: v.Año: 2011 | M74: Establece resguardos y medidas para asegurar la continuidad de servicios... | N74: https://digital.gob.cl/biblioteca/regulacion/
A75: Ley 20500 | B75: =if(A75="","", countif(Obligaciones!$D$3:$D$20388,A75)) -> 0 | C75: Ley | D75: Original | F75: https://bcn.cl/2f7nb | G75: Ministerio Secretaría General de la Presidencia | H75: Sobre asociaciones y participación ciudadana en la gestión pública | I75: 40590 | J75: 45064 | K75: Ley N° 20.500, sobre asociaciones y participación ciudadana en la gestión pública. | L75: Fecha de publicación: v.Año: 2011 | M75: Establece mecanismos de participación ciudadana en la gestión pública. | N75: https://digital.gob.cl/biblioteca/regulacion/
B76: =if(A76="","", countif(Obligaciones!$D$3:$D$20388,A76))
A77: Ley 19223 | B77: =if(A77="","", countif(Obligaciones!$D$3:$D$20388,A77)) -> 0 | C77: Ley | D77: Original | F77: https://bcn.cl/2gf9s | G77: Ministerio de Justicia | H77: Sobre delitos informáticos | I77: 34127 | J77: 45064 | K77: Ley N° 19.223 Tipifica Figuras Penales Relativas a la Informática | L77: Fecha de publicación: v.Año: 1993 | M77: Establece tipos de delitos informáticos y sus sanciones. | N77: https://digital.gob.cl/biblioteca/regulacion/
A78: DS MINREL 2017-83 | B78: =if(A78="","", countif(Obligaciones!$D$3:$D$20388,A78)) -> 0 | C78: Decreto | D78: Complementa a | E78: Ley 19223 | F78: https://bcn.cl/2ij3n | G78: Ministerio de Relaciones Exteriores | H78: Sobre la ciberdelincuencia | I78: 42975 | J78: 45064 | K78: DECRETO 83 PROMULGA EL CONVENIO SOBRE LA CIBERDELINCUENCIA. MINISTERIO DE RELACIONES EXTERIORES
A79: Política Nacional de Ciberseguridad 2017-2022 | B79: =if(A79="","", countif(Obligaciones!$D$3:$D$20388,A79)) -> 619 | C79: Política | D79: Original | F79: https://digital.gob.cl/biblioteca/estrategias/politica-nacional-de-ciberseguridad-2017-2022/ | G79: Ministerio del Interior y Seguridad Pública | H79: Sobre ciberseguridad | I79: 42763 | J79: 45064 | K79: Política Nacional de Ciberseguridad 2017-2022. Acerca de esta publicación: Lineamientos de política en materia de ciberseguridad, con una mirada que apunta al año 2022, para alcanzar el objetivo de contar con un ciberespacio libre, abierto, seguro y resiliente. Autor: Ministerio de Interior y Seguridad Pública Fecha de publicación: 28/01/2017, v.Año: 2017 Extracto: Establece un diagnóstico y hoja de ruta e iniciativas para avanzar en la la seguridad pública, las infraestructuras críticas, el gobierno digital, los intereses esenciales y la seguridad exterior de Chile.
A80: Decreto MINDEF Política de ciberdefensa 2018-3 | B80: =if(A80="","", countif(Obligaciones!$D$3:$D$20388,A80)) -> 54 | C80: Decreto | D80: Original | F80: https://bcn.cl/2n707 | G80: Ministerio de Defensa | H80: Sobre la ciberdefensa | I80: 43168 | J80: 45064 | K80: DECRETO 3 APRUEBA POLÍTICA DE CIBERDEFENSA. MINISTERIO DE DEFENSA NACIONAL
A81: Ley 21113 | B81: =if(A81="","", countif(Obligaciones!$D$3:$D$20388,A81)) -> 0 | C81: Ley | D81: Original | F81: https://bcn.cl/2q6es | G81: Ministerio del Interior | H81: Sobre ciberseguridad | I81: 43374 | J81: 45064 | K81: LEY 21113 Firma electrónica DECLARA EL MES DE OCTUBRE COMO EL MES NACIONAL DE LA CIBERSEGURIDAD. MINISTERIO DEL INTERIOR Y SEGURIDAD PÚBLICA
A82: Ley 21459 | B82: =if(A82="","", countif(Obligaciones!$D$3:$D$20388,A82)) -> 0 | C82: Ley | D82: Deroga a | E82: Ley 19223 | F82: https://bcn.cl/32uaf | G82: Ministerio de Justicia y Derechos Humanos | H82: Sobre delitos informáticos | I82: 44732 | J82: 45064 | K82: LEY 21459 Firma electrónica ESTABLECE NORMAS SOBRE DELITOS INFORMÁTICOS, DEROGA LA LEY N° 19.223 Y MODIFICA OTROS CUERPOS LEGALES CON EL OBJETO DE ADECUARLOS AL CONVENIO DE BUDAPEST. MINISTERIO DE JUSTICIA Y DERECHOS HUMANOS
A83: Decreto MININTERIOR 2022-273 | B83: =if(A83="","", countif(Obligaciones!$D$3:$D$20388,A83)) -> 0 | C83: Reglamento | D83: Original | F83: https://bcn.cl/3agqm | G83: Ministerio del Interior | H83: Sobre incidentes de ciberseguridad | I83: 44897 | J83: 45064 | K83: DECRETO 273 ESTABLECE OBLIGACIÓN DE REPORTAR INCIDENTES DE CIBERSEGURIDAD. MINISTERIO DEL INTERIOR Y SEGURIDAD PÚBLICA; SUBSECRETARÍA DEL INTERIOR
A84: Decreto MININT Crea Comité Interministerial sobre ciberseguridad 2015-533 | B84: =if(A84="","", countif(Obligaciones!$D$3:$D$20388,A84)) -> 0 | C84: Reglamento | D84: Original | F84: https://bcn.cl/2kbyz | G84: Ministerio del Interior y Seguridad Pública | H84: Sobre la institucionalidad del Comité Interministerial sobre ciberseguridad | I84: 42202 | J84: 45064 | K84: DECRETO 533 CREA COMITÉ INTERMINISTERIAL SOBRE CIBERSEGURIDAD MINISTERIO DEL INTERIOR Y SEGURIDAD PÚBLICA; SUBSECRETARÍA DEL INTERIOR
A85: Decreto MININT Crea Comité Interministerial sobre ciberseguridad 2020-579 | B85: =if(A85="","", countif(Obligaciones!$D$3:$D$20388,A85)) -> 0 | C85: Reglamento | D85: Modifica a | E85: Decreto MININT Crea Comité Interministerial sobre ciberseguridad 2015-533 | F85: https://bcn.cl/2nrxg | G85: Ministerio del Interior y Seguridad Pública | H85: Sobre la institucionalidad del Comité Interministerial sobre ciberseguridad | I85: 43837 | J85: 45064 | K85: DECRETO 579 MODIFICA DECRETO SUPREMO Nº 533, DE 2015, DEL MINISTERIO DEL INTERIOR Y SEGURIDAD PÚBLICA, QUE CREA COMITÉ INTERMINISTERIAL SOBRE CIBERSEGURIDAD. MINISTERIO DEL INTERIOR Y SEGURIDAD PÚBLICA; SUBSECRETARÍA DEL INTERIOR
A87: Decreto MINCTCI Política nacional de inteligencia artificial 2021-20 | B87: =if(A87="","", countif(Obligaciones!$D$3:$D$20388,A87)) -> 718 | C87: Reglamento | D87: Original | F87: https://bcn.cl/2uo23 | G87: Ministerio de Ciencia, Tecnología, Conocimiento e Innovación | H87: Sobre la política nacional de inteligencia artificial | I87: 44533 | J87: 45064 | K87: DECRETO 20 APRUEBA POLÍTICA NACIONAL DE INTELIGENCIA ARTIFICIAL. MINISTERIO DE CIENCIA, TECNOLOGÍA, CONOCIMIENTO E INNOVACIÓN
B88: =if(A88="","", countif(Obligaciones!$D$3:$D$20388,A88))
A89: Ley 19886 | B89: =if(A89="","", countif(Obligaciones!$D$3:$D$20388,A89)) -> 0 | C89: Ley | D89: Original | F89: https://bcn.cl/2f72u | G89: Ministerio de Hacienda | H89: Sobre contratos administrativos de suministro y prestación de servicios | I89: 37832 | J89: 45064 | K89: Ley N° 19.886, de Bases sobre Contratos Administrativos de Suministro y Prestación de Servicios; | L89: Fecha de publicación: v.Año: 2003 | M89: Ley que establece los procedimientos para contratación y adquisición de... | N89: https://digital.gob.cl/biblioteca/regulacion/
A90: Decreto MINDHA Contratos administrativos de suministro y prestación de servicios 2004-250 | B90: =if(A90="","", countif(Obligaciones!$D$3:$D$20388,A90)) -> 986 | C90: Reglamento | D90: Original | F90: https://bcn.cl/2f6fl | G90: Ministerio de Hacienda | H90: Sobre contratos administrativos de suministro y prestación de servicios | I90: 38254 | J90: 45064 | K90: DECRETO 250 APRUEBA REGLAMENTO DE LA LEY Nº19.886 DE BASES SOBRE CONTRATOS ADMINISTRATIVOS DE SUMINISTRO Y PRESTACION DE SERVICIOS. MINISTERIO DE HACIENDA
B91: =if(A91="","", countif(Obligaciones!$D$3:$D$20388,A91))
A92: Ley 20285 | B92: =if(A92="","", countif(Obligaciones!$D$3:$D$20388,A92)) -> 0 | C92: Ley | D92: Original | F92: https://bcn.cl/2f8ep | G92: Ministerio Secretaría General de la Presidencia | H92: Sobre acceso a la información pública | I92: 39680 | J92: 45064 | K92: Ley N° 20.285, sobre Acceso a la Información Pública; | L92: Fecha de publicación: v.Año: 2008 | M92: Ley que regula y establece los mecanismos de transparencia de la... | N92: https://digital.gob.cl/biblioteca/regulacion/
A93: Directiva CHILECOMPRA 2018-32 | B93: =if(A93="","", countif(Obligaciones!$D$3:$D$20388,A93)) -> 0 | C93: Directiva | D93: Original | F93: https://www.chilecompra.cl/2018/12/directiva-n32/ | G93: ChileCompra | H93: Sobre contratación pública | I93: 43430 | J93: 45064 | K93: Diciembre 5, 2018 Directiva N°32. Aprueba Directiva de Contratación Pública N°32 “Recomendaciones para la contratación de servicios en la nube”. Resolución 619-B. 26 de noviembre de 2018
B94: =if(A94="","", countif(Obligaciones!$D$3:$D$20388,A94))
A95: Decreto MININT 2022-273 | B95: =if(A95="","", countif(Obligaciones!$D$3:$D$20388,A95)) -> 37 | C95: Reglamento | D95: Original | F95: https://bcn.cl/3agqm | G95: Ministerio del Interior y Seguridad Pública | I95: 44897 | J95: 45064 | K95: DECRETO 273 ESTABLECE OBLIGACIÓN DE REPORTAR INCIDENTES DE CIBERSEGURIDAD. MINISTERIO DEL INTERIOR Y SEGURIDAD PÚBLICA; SUBSECRETARÍA DEL INTERIOR
A97: Guía MINSEGPRES Fase de Preparación Grupo A | B97: =if(A97="","", countif(Obligaciones!$D$3:$D$20388,A97)) -> 217 | C97: Guía | D97: Original | F97: https://digital.gob.cl/transformacion-digital/estandares-y-guias/guia-resumen-fase-de-preparacion-ley-n21180-grupo-a/ | G97: Ministerio Secretaría General de la Presidencia | H97: Sobre la fase de preparación Ley Nº 21.180 | I97: 44606 | J97: 45064 | K97: Guía Resumen Fase de Preparación Ley N°21.180, Grupo A. División de Gobierno Digital, SEGPRES. Fecha de publicación: 03/03/2023, v.3 Extracto: El principal objetivo de la fase de preparación, es que los órganos avancen en la identificación de sus procedimientos administrativos, como la unidad básica sobre la cual deberán trabajar para llevarlos a soporte electrónico.
A98: Guía MINSEGPRES Fase de Preparación Grupo C | B98: =if(A98="","", countif(Obligaciones!$D$3:$D$20388,A98)) -> 224 | C98: Guía | D98: Original | F98: https://digital.gob.cl/transformacion-digital/estandares-y-guias/guia-resumen-fase-de-preparacion-ley-n21180-grupo-c/ | G98: Ministerio Secretaría General de la Presidencia | H98: Sobre la fase de preparación Ley Nº 21.180 | I98: 44988 | J98: 45064 | K98: Guía Resumen Fase de Preparación Ley N°21.180, Grupo C. División de Gobierno Digital, SEGPRES Fecha de publicación: 03/03/2023, v.1 Extracto: El principal objetivo de la fase de preparación, es que los órganos avancen en la identificación de sus procedimientos administrativos, como la unidad básica sobre la cual deberán trabajar para llevarlos a soporte electrónico.
A99: Guía MINSEGPRES Fase de Preparación Grupo B | B99: =if(A99="","", countif(Obligaciones!$D$3:$D$20388,A99)) -> 225 | C99: Guía | D99: Original | F99: https://digital.gob.cl/transformacion-digital/estandares-y-guias/guia-resumen-fase-de-preparacion-ley-n21180-sobre-transformacion-digital-del-estado-grupo-b/ | G99: Ministerio Secretaría General de la Presidencia | H99: Sobre la fase de preparación Ley Nº 21.180 | I99: 44988 | J99: 45064 | K99: Guía Resumen Fase de Preparación Ley N°21.180, Grupo B. División de Gobierno Digital, SEGPRES Fecha de publicación: 03/03/2023, v.1 Extracto: El principal objetivo de la fase de preparación, es que los órganos avancen en la identificación de sus procedimientos administrativos, como la unidad básica sobre la cual deberán trabajar para llevarlos a soporte electrónico.
A100: Orientaciones técnicas fase de preparación DGD 2023-1 | B100: =if(A100="","", countif(Obligaciones!$D$3:$D$20388,A100)) -> 300 | C100: Guía | D100: Original | F100: https://digital.gob.cl/transformacion-digital/estandares-y-guias/guia-resumen-sobre-la-ley-de-transformacion-digital-del-estado/ | G100: División de Gobierno Digital | H100: Sobre la fase de preparación Ley Nº 21.180 | I100: 44953 | J100: 45064 | K100: Orientaciones Técnicas para la fase de Preparación. Acerca de esta publicación: Este documento incluye las principales acciones que deberán realizar los OAE en el marco de la fase de preparación de la ley de Transformación Digital, con foco en el levantamiento de sus procedimientos administrativos. Autor: División de Gobierno Digital Fecha de publicación: 05/08/2022, v.V.2. Extracto: El presente documento, tiene por objeto entregar las acciones que los OAE deberán llevar a cabo en las fases iniciales de implementación, y en particular lo relativo a la identificación y caracterización de los procedimientos administrativos, como unidad básica sobre la cual se trabajará en los años posteriores para realizarse completamente en forma electrónica, de acuerdo a estándares tecnológicos comunes y plataformas habilitantes transversales que forman parte del ecosistema de implementación de la ley.
A101: Guía de levantamiento de procesos | B101: =if(A101="","", countif(Obligaciones!$D$3:$D$20388,A101)) -> 1059 | C101: Guía | D101: Original | F101: https://digital.gob.cl/transformacion-digital/estandares-y-guias/guia-de-levantamiento-de-procesos/ | G101: División de Gobierno Digital | H101: Sobre la fase de preparación Ley Nº 21.180 | I101: 44923 | J101: 45064 | K101: Guía de levantamiento de procesos. Acerca de esta publicación: Documento que contiene una guía con un marco metodológico de apoyo sobre la gestión de procesos, permitiendo a las instituciones contar con una herramienta práctica de trabajo sobre esta materia y que puedan compartir con sus respectivos equipos. Autor: Equipo de Trámites y Procedimientos DGD Fecha de publicación: 28/12/2022, v.1 Extracto: Como parte de la fase de preparación, la DGD ha disponibilizado documentos de trabajo que apoyen el proceso de implementación a través de documentos con lineamientos, documento de marco conceptual de procedimientos administrativos, preguntas frecuentes, entre otros.
A102: Guía de proyectos de ciencia de datos | B102: =if(A102="","", countif(Obligaciones!$D$3:$D$20388,A102)) -> 0 | C102: Guía | D102: Original | F102: https://digital.gob.cl/transformacion-digital/estandares-y-guias/guia-formulacion-etica-de-proyectos-de-ciencia-de-datos/ | G102: División de Gobierno Digital | H102: Sobre la formulación ética de proyectos de ciencia de datos | I102: 44797 | J102: 45064 | K102: Guía Formulación Ética de Proyectos de Ciencia de Datos. Acerca de esta publicación: El documento fue desarrollado en conjunto por investigadores de la UAI y profesionales de la DGD y su objetivo es orientar a funcionarios/as e instituciones públicas para que consideren y prevengan riesgos éticos y legales al desarrollar proyectos tecnológicos que involucran el uso y análisis intensivo de datos. Autor: Universidad Adolfo Ibáñez - División de Gobierno Digital. Fecha de publicación: 24/08/2022, v.1. Extracto: A través de una metodología clara y ejemplos concretos ajustados a la realidad y la normativa chilena, la guía será un valioso apoyo para planificar, formular y desarrollar sistemas de toma de decisión o de soporte a la toma de decisión basados en inteligencia artificial o modelos algorítmicos, evitando sesgos de discriminación, falta de transparencia o mal uso de datos personales, entre otros potenciales problemas.
A104: Ley 21118 | C104: Ley | D104: Original | F104: https://bcn.cl/2fd6x | G104: Ministerio de Energía | H104: LEY 21118 MODIFICA LA LEY GENERAL DE SERVICIOS ELÉCTRICOS, CON EL FIN DE INCENTIVAR EL DESARROLLO DE LAS GENERADORAS RESIDENCIALES. MINISTERIO DE ENERGÍA
A106: Guía SENADIS para la implementación de sitios Web Accesibles | C106: Instructivo | D106: Original | F106: https://www.senadis.gob.cl/descarga/i/3676/documento | G106: Servicio Nacional de la Discapacidad | H106: Guía técnica para la implementación de sitios Web Accesibles. Instructivos de la SENADIS | I106: 42656
A107: Decreto MINSEGPRES 2015-1 | C107: Norma Técnica | D107: Original | F107: https://bcn.cl/2m5gb | G107: Ministerio Secretaría General de la Presidencia | H107: DECRETO 1 APRUEBA NORMA TÉCNICA SOBRE SISTEMAS Y SITIOS WEB DE LOS ÓRGANOS DE LA ADMINISTRACIÓN DEL ESTADO. MINISTERIO SECRETARÍA GENERAL DE LA PRESIDENCIA | I107: 42166
H109: Agenda de Modernización del Estado 2022-2026
G111: SUBDERE | H111: 11. ANTECEDENTES RELEVANTES PARA EL SERVICIO
H112: Las siguientes referencias deben considerarse como antecedentes importantes para los planteamientos metodológicos y el desarrollo de las tareas de la presente contratación:
H113: 11.1. Ley de Transformación Digital del Estado N° 21.180 del 25.10.2019
H114: 11.2. Ley N°21.464, modifica diversos cuerpos legales, en materia de Transformación Digital del Estado.
...

Sheet Obligaciones
A1: Obligaciones normativas en materia de Transformación Digital del Estado de Chile
C2: =CONCATENATE(COUNTIF($A$601:$A$648,TRUE), "/", COUNTA($C$601:$C$648), " completed ") -> 0/1 completed
A3: ✓ | B3: Evento/Periodicidad | C3: Obligación | D3: Referencia normativa | E3: Tipo_de_norma | F3: Obligación, definición | G3: Alcance | H3: Texto | I3: n_text | J3: Plan de acción que debe tener cada Órgano de la Administración del Estado (OAE) | K3: Obligación del Estado
A4: FALSE | D4: Ley 19880 | E4: =VLOOKUP(D4,Normativa!$A$3:$C$100,3,0) -> Ley | H4: ESTABLECE BASES DE LOS PROCEDIMIENTOS ADMINISTRATIVOS QUE RIGEN LOS ACTOS DE LOS ORGANOS DE LA ADMINISTRACION DEL ESTADO | I4: =IF(H4=H3,I3+1,1) -> 1
A5: FALSE | D5: Ley 19880 | E5: =VLOOKUP(D5,Normativa!$A$3:$C$100,3,0) -> Ley | I5: =IF(H5=H4,I4+1,1) -> 1
A6: FALSE | D6: Ley 19880 | E6: =VLOOKUP(D6,Normativa!$A$3:$C$100,3,0) -> Ley | H6: Teniendo presente que el H. Congreso Nacional ha dado su aprobación al siguiente | I6: =IF(H6=H5,I5+1,1) -> 1
A7: FALSE | D7: Ley 19880 | E7: =VLOOKUP(D7,Normativa!$A$3:$C$100,3,0) -> Ley | I7: =IF(H7=H6,I6+1,1) -> 1
A8: FALSE | D8: Ley 19880 | E8: =VLOOKUP(D8,Normativa!$A$3:$C$100,3,0) -> Ley | H8: Proyecto de ley: | I8: =IF(H8=H7,I7+1,1) -> 1
A9: FALSE | D9: Ley 19880 | E9: =VLOOKUP(D9,Normativa!$A$3:$C$100,3,0) -> Ley | I9: =IF(H9=H8,I8+1,1) -> 1
A10: FALSE | D10: Ley 19880 | E10: =VLOOKUP(D10,Normativa!$A$3:$C$100,3,0) -> Ley | I10: =IF(H10=H9,I9+1,1) -> 2
A11: FALSE | D11: Ley 19880 | E11: =VLOOKUP(D11,Normativa!$A$3:$C$100,3,0) -> Ley | I11: =IF(H11=H10,I10+1,1) -> 3
A12: FALSE | D12: Ley 19880 | E12: =VLOOKUP(D12,Normativa!$A$3:$C$100,3,0) -> Ley | I12: =IF(H12=H11,I11+1,1) -> 4
A13: FALSE | D13: Ley 19880 | E13: =VLOOKUP(D13,Normativa!$A$3:$C$100,3,0) -> Ley | I13: =IF(H13=H12,I12+1,1) -> 5
A14: FALSE | B14: En la tramitación de un procedimiento administrativo | C14: Todo procedimiento administrativo deberá expresarse a través de los medios electrónicos establecidos por ley, salvo las excepciones legales. En caso de que la ley establezca procedimientos administrativos especiales, la presente ley se aplicará con carácter supletorio. | D14: Ley 19880 | E14: =VLOOKUP(D14,Normativa!$A$3:$C$100,3,0) -> Ley | F14: Obligación | G14: Órganos de la Administración del Estado | H14: CAPITULO I Disposiciones Generales Artículo 1º. Procedimiento Administrativo. La presente ley establece y regula las bases del procedimiento administrativo de los actos de la Administración del Estado. Todo procedimiento administrativo deberá expresarse a través de los medios electrónicos establecidos por ley, salvo las excepciones legales. En caso de que la ley establezca procedimientos administrativos especiales, la presente ley se aplicará con carácter supletorio. La toma de razón de los actos de la Administración del Estado se regirán por lo dispuesto en la Constitución y en la Ley Orgánica Constitucional de la Contraloría General de la República. | I14: =IF(H14=H13,I13+1,1) -> 1
A15: FALSE | D15: Ley 19880 | E15: =VLOOKUP(D15,Normativa!$A$3:$C$100,3,0) -> Ley | H15: Artículo 2º. Ambito de aplicación. Las disposiciones de la presente ley serán aplicables a los ministerios, las intendencias, las gobernaciones y los servicios públicos creados para el cumplimiento de la función administrativa. También se aplicarán a la Contraloría General de la República, a las Fuerzas Armadas y a las Fuerzas de Orden y Seguridad Pública, a los gobiernos regionales y a las municipalidades. Las referencias que esta ley haga a la Administración o a la Administración del Estado, se entenderán efectuadas a los órganos y organismos señalados en el inciso precedente | I15: =IF(H15=H14,I14+1,1) -> 1
A16: FALSE | D16: Ley 19880 | E16: =VLOOKUP(D16,Normativa!$A$3:$C$100,3,0) -> Ley | H16: Artículo 3º. Concepto de Acto administrativo. Las decisiones escritas que adopte la Administración se expresarán por medio de actos administrativos. Para efectos de esta ley se entenderá por acto administrativo las decisiones formales que emitan los órganos de la Administración del Estado en las cuales se contienen declaraciones de voluntad, realizadas en el ejercicio de una potestad pública. Los actos administrativos tomarán la forma de decretos supremos y resoluciones. El decreto supremo es la orden escrita que dicta el Presidente de la República o un Ministro Por orden del Presidente de la República", sobre asuntos propios de su competencia. | I16: =IF(H16=H15,I15+1,1) -> 1
A17: FALSE | D17: Ley 19880 | E17: =VLOOKUP(D17,Normativa!$A$3:$C$100,3,0) -> Ley | H17: Las resoluciones son los actos de análoga naturaleza que dictan las autoridades administrativas dotadas de poder de decisión. | I17: =IF(H17=H16,I16+1,1) -> 1
A18: FALSE | D18: Ley 19880 | E18: =VLOOKUP(D18,Normativa!$A$3:$C$100,3,0) -> Ley | H18: Constituyen, también, actos administrativos los dictámenes o declaraciones de juicio, constancia o conocimiento que realicen los órganos de la Administración en el ejercicio de sus competencias. | I18: =IF(H18=H17,I17+1,1) -> 1
A19: FALSE | D19: Ley 19880 | E19: =VLOOKUP(D19,Normativa!$A$3:$C$100,3,0) -> Ley | H19: Las decisiones de los órganos administrativos pluripersonales se denominan acuerdos y se llevan a efecto por medio de resoluciones de la autoridad ejecutiva de la entidad correspondiente. | I19: =IF(H19=H18,I18+1,1) -> 1
A20: FALSE | D20: Ley 19880 | E20: =VLOOKUP(D20,Normativa!$A$3:$C$100,3,0) -> Ley | H20: Los actos administrativos gozan de una presunción de legalidad, de imperio y exigibilidad frente a sus destinatarios, desde su entrada en vigencia, autorizando su ejecución de oficio por la autoridad administrativa, salvo que mediare una orden de suspensión dispuesta por la autoridad administrativa dentro del procedimiento impugnatorio o por el juez, conociendo por la vía jurisdiccional. | I20: =IF(H20=H19,I19+1,1) -> 1
A21: FALSE | D21: Ley 19880 | E21: =VLOOKUP(D21,Normativa!$A$3:$C$100,3,0) -> Ley | I21: =IF(H21=H20,I20+1,1) -> 1
A22: FALSE | D22: Ley 19880 | E22: =VLOOKUP(D22,Normativa!$A$3:$C$100,3,0) -> Ley | H22: Artículo 4º. Principios del procedimiento. El procedimiento administrativo estará sometido a los principios de escrituración, gratuidad, celeridad, conclusivo, economía procedimental, contradictoriedad, imparcialidad, abstención, no formalización, inexcusabilidad, impugnabilidad, transparencia, publicidad y aquellos relativos a los medios electrónicos. | I22: =IF(H22=H21,I21+1,1) -> 1
A23: FALSE | D23: Ley 19880 | E23: =VLOOKUP(D23,Normativa!$A$3:$C$100,3,0) -> Ley | I23: =IF(H23=H22,I22+1,1) -> 1
A24: FALSE | D24: Ley 19880 | E24: =VLOOKUP(D24,Normativa!$A$3:$C$100,3,0) -> Ley | I24: =IF(H24=H23,I23+1,1) -> 2
A25: FALSE | D25: Ley 19880 | E25: =VLOOKUP(D25,Normativa!$A$3:$C$100,3,0) -> Ley | I25: =IF(H25=H24,I24+1,1) -> 3
A26: FALSE | D26: Ley 19880 | E26: =VLOOKUP(D26,Normativa!$A$3:$C$100,3,0) -> Ley | H26: Artículo 5º. Principio de escrituración. El procedimiento administrativo y los actos administrativos a los cuales da origen se expresarán por escrito a través de medios electrónicos, a menos que se configure alguna excepción establecida en la ley. | I26: =IF(H26=H25,I25+1,1) -> 1
A27: FALSE | D27: Ley 19880 | E27: =VLOOKUP(D27,Normativa!$A$3:$C$100,3,0) -> Ley | I27: =IF(H27=H26,I26+1,1) -> 1
A28: FALSE | D28: Ley 19880 | E28: =VLOOKUP(D28,Normativa!$A$3:$C$100,3,0) -> Ley | H28: Artículo 6º. Principio de gratuidad. En el procedimiento administrativo, las actuaciones que deban practicar los órganos de la Administración del Estado y la obtención de documentos e información necesaria para su conclusión serán gratuitas para los interesados, salvo disposición legal en contrario. No procederán cobros entre los órganos de la Administración del Estado que deban participar en su desarrollo e intercambio, salvo disposición legal en contrario. | I28: =IF(H28=H27,I27+1,1) -> 1
A29: FALSE | D29: Ley 19880 | E29: =VLOOKUP(D29,Normativa!$A$3:$C$100,3,0) -> Ley | I29: =IF(H29=H28,I28+1,1) -> 1
A30: FALSE | D30: Ley 19880 | E30: =VLOOKUP(D30,Normativa!$A$3:$C$100,3,0) -> Ley | H30: Artículo 7º. Principio de celeridad. El procedimiento, sometido al criterio de celeridad, se impulsará de oficio en todos sus trámites. | I30: =IF(H30=H29,I29+1,1) -> 1
A31: FALSE | D31: Ley 19880 | E31: =VLOOKUP(D31,Normativa!$A$3:$C$100,3,0) -> Ley | H31: Las autoridades y funcionarios de los órganos de la Administración del Estado deberán actuar por propia iniciativa en la iniciación del procedimiento de que se trate y en su prosecución, haciendo expeditos los trámites que debe cumplir el expediente y removiendo todo obstáculo que pudiere afectar a su pronta y debida decisión. | I31: =IF(H31=H30,I30+1,1) -> 1
A32: FALSE | D32: Ley 19880 | E32: =VLOOKUP(D32,Normativa!$A$3:$C$100,3,0) -> Ley | H32: En el despacho de los expedientes originados en una solicitud o en el ejercicio de un derecho se guardará el orden riguroso de ingreso en asuntos de similar naturaleza, salvo que por el titular de la unidad administrativa se dé orden motivada en contrario, de la que quede constancia. | I32: =IF(H32=H31,I31+1,1) -> 1
A33: FALSE | D33: Ley 19880 | E33: =VLOOKUP(D33,Normativa!$A$3:$C$100,3,0) -> Ley | H33: Artículo 8º. Principio conclusivo. Todo el procedimiento administrativo está destinado a que la Administración dicte un acto decisorio que se pronuncie sobre la cuestión de fondo y en el cual exprese su voluntad. | I33: =IF(H33=H32,I32+1,1) -> 1
A34: FALSE | D34: Ley 19880 | E34: =VLOOKUP(D34,Normativa!$A$3:$C$100,3,0) -> Ley | H34: Artículo 9º. Principio de economía procedimental. La Administración debe responder a la máxima economía de medios con eficacia, evitando trámites dilatorios. | I34: =IF(H34=H33,I33+1,1) -> 1
A35: FALSE | D35: Ley 19880 | E35: =VLOOKUP(D35,Normativa!$A$3:$C$100,3,0) -> Ley | H35: Se decidirán en un solo acto todos los trámites que, por su naturaleza, admitan un impulso simultáneo, siempre que no sea obligatorio su cumplimiento sucesivo. | I35: =IF(H35=H34,I34+1,1) -> 1
A36: FALSE | B36: Siempre que ocurra una comunicación entre órganos de la Administración | C36: Toda comunicación entre órganos de la Administración que se practique en el marco del procedimiento se realizará por medios electrónicos, dejándose constancia del órgano requirente, el funcionario responsable que practica el requerimiento, destinatario, procedimiento a que corresponde, gestión que se encarga y el plazo establecido para su realización. | D36: Ley 19880 | E36: =VLOOKUP(D36,Normativa!$A$3:$C$100,3,0) -> Ley | F36: Obligación | G36: Órganos de la Administración del Estado | H36: Toda comunicación entre órganos de la Administración que se practique en el marco del procedimiento se realizará por medios electrónicos, dejándose constancia del órgano requirente, el funcionario responsable que practica el requerimiento, destinatario, procedimiento a que corresponde, gestión que se encarga y el plazo establecido para su realización. Asimismo, deberá remitirse una copia electrónica de tal comunicación a todos quienes figuren como interesados en el procedimiento administrativo de que se trate. | I36: =IF(H36=H35,I35+1,1) -> 1 | J36: Se cumple con la implementación de docDigital en todos los Órganos de la Administración del Estado
A37: FALSE | D37: Ley 19880 | E37: =VLOOKUP(D37,Normativa!$A$3:$C$100,3,0) -> Ley | H37: Las cuestiones incidentales que se susciten en el procedimiento, incluso las que se refieran a la nulidad de actuaciones, no suspenderán la tramitación del mismo, a menos que la Administración, por resolución fundada, determine lo contrario. | I37: =IF(H37=H36,I36+1,1) -> 1
A38: FALSE | D38: Ley 19880 | E38: =VLOOKUP(D38,Normativa!$A$3:$C$100,3,0) -> Ley | I38: =IF(H38=H37,I37+1,1) -> 1
A39: FALSE | D39: Ley 19880 | E39: =VLOOKUP(D39,Normativa!$A$3:$C$100,3,0) -> Ley | H39: Artículo 10. Principio de contradictoriedad. Los interesados podrán, en cualquier momento del procedimiento, aducir alegaciones y aportar documentos u otros elementos de juicio. | I39: =IF(H39=H38,I38+1,1) -> 1
A40: FALSE | D40: Ley 19880 | E40: =VLOOKUP(D40,Normativa!$A$3:$C$100,3,0) -> Ley | H40: Los interesados podrán, en todo momento, alegar defectos de tramitación, especialmente los que supongan paralización, infracción de los plazos señalados o la omisión de trámites que pueden ser subsanados antes de la resolución definitiva del asunto. Dichas alegaciones podrán dar lugar, si hubiere razones para ello, a la exigencia de la correspondiente responsabilidad disciplinaria. | I40: =IF(H40=H39,I39+1,1) -> 1
A41: FALSE | D41: Ley 19880 | E41: =VLOOKUP(D41,Normativa!$A$3:$C$100,3,0) -> Ley | H41: Los interesados podrán, en todo caso, actuar asistidos de asesor cuando lo consideren conveniente en defensa de sus intereses. | I41: =IF(H41=H40,I40+1,1) -> 1
A42: FALSE | D42: Ley 19880 | E42: =VLOOKUP(D42,Normativa!$A$3:$C$100,3,0) -> Ley | H42: En cualquier caso, el órgano instructor adoptará las medidas necesarias para lograr el pleno respeto a los principios de contradicción y de igualdad de los interesados en el procedimiento. | I42: =IF(H42=H41,I41+1,1) -> 1
A43: FALSE | D43: Ley 19880 | E43: =VLOOKUP(D43,Normativa!$A$3:$C$100,3,0) -> Ley | H43: Artículo 11. Principio de imparcialidad. La Administración debe actuar con objetividad y respetar el principio de probidad consagrado en la legislación, tanto en la substanciación del procedimiento como en las decisiones que adopte. | I43: =IF(H43=H42,I42+1,1) -> 1
A44: FALSE | D44: Ley 19880 | E44: =VLOOKUP(D44,Normativa!$A$3:$C$100,3,0) -> Ley | H44: Los hechos y fundamentos de derecho deberán siempre expresarse en aquellos actos que afectaren los derechos de los particulares, sea que los limiten, restrinjan, priven de ellos, perturben o amenacen su legítimo ejercicio, así como aquellos que resuelvan recursos administrativos. | I44: =IF(H44=H43,I43+1,1) -> 1
A45: FALSE | D45: Ley 19880 | E45: =VLOOKUP(D45,Normativa!$A$3:$C$100,3,0) -> Ley | H45: Artículo 12. Principio de abstención. Las autoridades y los funcionarios de la Administración en quienes se den algunas de las circunstancias señaladas a continuación, se abstendrán de intervenir en el procedimiento y lo comunicarán a su superior inmediato, quien resolverá lo procedente. | I45: =IF(H45=H44,I44+1,1) -> 1
A46: FALSE | D46: Ley 19880 | E46: =VLOOKUP(D46,Normativa!$A$3:$C$100,3,0) -> Ley | I46: =IF(H46=H45,I45+1,1) -> 1
A47: FALSE | D47: Ley 19880 | E47: =VLOOKUP(D47,Normativa!$A$3:$C$100,3,0) -> Ley | H47: Son motivos de abstención los siguientes: | I47: =IF(H47=H46,I46+1,1) -> 1
A48: FALSE | D48: Ley 19880 | E48: =VLOOKUP(D48,Normativa!$A$3:$C$100,3,0) -> Ley | I48: =IF(H48=H47,I47+1,1) -> 1
A49: FALSE | D49: Ley 19880 | E49: =VLOOKUP(D49,Normativa!$A$3:$C$100,3,0) -> Ley | H49: 1. Tener interés personal en el asunto de que se trate o en otro en cuya resolución pudiera influir la de aquél; ser administrador de sociedad o entidad interesada, o tener cuestión litigiosa pendiente con algún interesado. | I49: =IF(H49=H48,I48+1,1) -> 1
A50: FALSE | D50: Ley 19880 | E50: =VLOOKUP(D50,Normativa!$A$3:$C$100,3,0) -> Ley | H50: 2. Tener parentesco de consanguinidad dentro del cuarto grado o de afinidad dentro del segundo, con cualquiera de los interesados, con los administradores de entidades o sociedades interesadas y también con los asesores, representantes legales o mandatarios que intervengan en el procedimiento, así como compartir despacho profesional o estar asociado con éstos para el asesoramiento, la representación o el mandato. | I50: =IF(H50=H49,I49+1,1) -> 1
A51: FALSE | D51: Ley 19880 | E51: =VLOOKUP(D51,Normativa!$A$3:$C$100,3,0) -> Ley | H51: 3. Tener amistad íntima o enemistad manifiesta con alguna de las personas mencionadas anteriormente. | I51: =IF(H51=H50,I50+1,1) -> 1
A52: FALSE | D52: Ley 19880 | E52: =VLOOKUP(D52,Normativa!$A$3:$C$100,3,0) -> Ley | H52: 4. Haber tenido intervención como perito o como testigo en el procedimiento de que se trate. | I52: =IF(H52=H51,I51+1,1) -> 1
A53: FALSE | D53: Ley 19880 | E53: =VLOOKUP(D53,Normativa!$A$3:$C$100,3,0) -> Ley | H53: 5. Tener relación de servicio con persona natural o jurídica interesada directamente en el asunto, o haberle prestado en los dos últimos años servicios profesionales de cualquier tipo y en cualquier circunstancia o lugar. | I53: =IF(H53=H52,I52+1,1) -> 1
A54: FALSE | D54: Ley 19880 | E54: =VLOOKUP(D54,Normativa!$A$3:$C$100,3,0) -> Ley | I54: =IF(H54=H53,I53+1,1) -> 1
A55: FALSE | D55: Ley 19880 | E55: =VLOOKUP(D55,Normativa!$A$3:$C$100,3,0) -> Ley | H55: La actuación de autoridades y los funcionarios de la Administración en los que concurran motivos de abstención no implicará, necesariamente, la invalidez de los actos en que hayan intervenido. | I55: =IF(H55=H54,I54+1,1) -> 1
A56: FALSE | D56: Ley 19880 | E56: =VLOOKUP(D56,Normativa!$A$3:$C$100,3,0) -> Ley | H56: La no abstención en los casos en que proceda dará lugar a responsabilidad. | I56: =IF(H56=H55,I55+1,1) -> 1
A57: FALSE | D57: Ley 19880 | E57: =VLOOKUP(D57,Normativa!$A$3:$C$100,3,0) -> Ley | H57: En los casos previstos en los incisos precedentes podrá promoverse inhabilitación por los interesados en cualquier momento de la tramitación del procedimiento. | I57: =IF(H57=H56,I56+1,1) -> 1
A58: FALSE | D58: Ley 19880 | E58: =VLOOKUP(D58,Normativa!$A$3:$C$100,3,0) -> Ley | H58: La inhabilitación se planteará ante la misma autoridad o funcionario afectado, por escrito, en el que se expresará la causa o causas en que se funda. | I58: =IF(H58=H57,I57+1,1) -> 1
A59: FALSE | D59: Ley 19880 | E59: =VLOOKUP(D59,Normativa!$A$3:$C$100,3,0) -> Ley | H59: Artículo 13. Principio de la no formalización. El procedimiento debe desarrollarse con sencillez y eficacia, de modo que las formalidades que se exijan sean aquéllas indispensables para dejar constancia indubitada de lo actuado y evitar perjuicios a los particulares. | I59: =IF(H59=H58,I58+1,1) -> 1
A60: FALSE | D60: Ley 19880 | E60: =VLOOKUP(D60,Normativa!$A$3:$C$100,3,0) -> Ley | H60: El vicio de procedimiento o de forma sólo afecta la validez del acto administrativo cuando recae en algún requisito esencial del mismo, sea por su naturaleza o por mandato del ordenamiento jurídico y genera perjuicio al interesado. | I60: =IF(H60=H59,I59+1,1) -> 1
A61: FALSE | D61: Ley 19880 | E61: =VLOOKUP(D61,Normativa!$A$3:$C$100,3,0) -> Ley | H61: La Administración podrá subsanar los vicios de que adolezcan los actos que emita, siempre que con ello no se afectaren intereses de terceros. | I61: =IF(H61=H60,I60+1,1) -> 1
A62: FALSE | D62: Ley 19880 | E62: =VLOOKUP(D62,Normativa!$A$3:$C$100,3,0) -> Ley | H62: Artículo 14. Principio de inexcusabilidad. La Administración estará obligada a dictar resolución expresa en todos los procedimientos y a notificarla, cualquiera que sea su forma de iniciación. | I62: =IF(H62=H61,I61+1,1) -> 1
A63: FALSE | D63: Ley 19880 | E63: =VLOOKUP(D63,Normativa!$A$3:$C$100,3,0) -> Ley | H63: Requerido un órgano de la Administración para intervenir en un asunto que no sea de su competencia, enviará de inmediato los antecedentes a la autoridad que deba conocer según el ordenamiento jurídico, informando de ello al interesado. | I63: =IF(H63=H62,I62+1,1) -> 1
A64: FALSE | D64: Ley 19880 | E64: =VLOOKUP(D64,Normativa!$A$3:$C$100,3,0) -> Ley | H64: En los casos de prescripción, renuncia del derecho, abandono del procedimiento o desistimiento de la solicitud, así como la desaparición sobreviniente del objeto del procedimiento, la resolución consistirá en la declaración de la circunstancia que concurra en cada caso, con indicación de los hechos producidos y las normas aplicables. | I64: =IF(H64=H63,I63+1,1) -> 1
A65: FALSE | D65: Ley 19880 | E65: =VLOOKUP(D65,Normativa!$A$3:$C$100,3,0) -> Ley | H65: Artículo 15. Principio de impugnabilidad. Todo acto administrativo es impugnable por el interesado mediante los recursos administrativos de reposición y jerárquico, regulados en esta ley, sin perjuicio del recurso extraordinario de revisión y de los demás recursos que establezcan las leyes especiales. | I65: =IF(H65=H64,I64+1,1) -> 1
A66: FALSE | D66: Ley 19880 | E66: =VLOOKUP(D66,Normativa!$A$3:$C$100,3,0) -> Ley | H66: Sin embargo, los actos de mero trámite son impugnables sólo cuando determinen la imposibilidad de continuar un procedimiento o produzcan indefensión. | I66: =IF(H66=H65,I65+1,1) -> 1
... A69: FALSE | D69: Ley 19880 | E69: =VLOOKUP(D69,Normativa!$A$3:$C$100,3,0) -> Ley | H69: En consecuencia, salvo las excepciones establecidas en la Ley de Transparencia de la Función Pública y de Acceso a la Información de la Administración del Estado y en otras disposiciones legales aprobadas con quórum calificado, son públicos los actos y resoluciones de los órganos de la Administración del Estado, así como sus fundamentos y documentos en que éstos se contengan, y los procedimientos que utilicen en su elaboración o dictación. | I69: =IF(H69=H68,I68+1,1) -> 1
A70: FALSE | D70: Ley 19880 | E70: =VLOOKUP(D70,Normativa!$A$3:$C$100,3,0) -> Ley | I70: =IF(H70=H69,I69+1,1) -> 1
A71: FALSE | D71: Ley 19880 | E71: =VLOOKUP(D71,Normativa!$A$3:$C$100,3,0) -> Ley | I71: =IF(H71=H70,I70+1,1) -> 2
A72: FALSE | D72: Ley 19880 | E72: =VLOOKUP(D72,Normativa!$A$3:$C$100,3,0) -> Ley | I72: =IF(H72=H71,I71+1,1) -> 3
A73: FALSE | B73: En la tramitación de un procedimiento administrativo por medios electrónicos | C73: En la tramitación de los procedimientos administrativos por medios electrónicos se deberá cumplir con el principio de neutralidad tecnológica | D73: Ley 19880 | E73: =VLOOKUP(D73,Normativa!$A$3:$C$100,3,0) -> Ley | F73: Obligación | G73: Órganos de la Administración del Estado | H73: Artículo 16 bis. Principios generales relativos a los medios electrónicos. En la tramitación de los procedimientos administrativos por medios electrónicos se deberá cumplir con los principios de neutralidad tecnológica, de actualización, de equivalencia funcional, de fidelidad, de interoperabilidad y de cooperación. | I73: =IF(H73=H72,I72+1,1) -> 1 | J73: Se cumple el principio de neutralidad tecnológica cuando el OAE brinda sus servicios permitiendo la libertad de los individuos y organizaciones de elegir la tecnología más adecuada para sus fines.
A74: FALSE | B74: En la tramitación de un procedimiento administrativo por medios electrónicos | C74: En la tramitación de los procedimientos administrativos por medios electrónicos se deberá cumplir con el principio de actualización. En virtud del principio de actualización, los órganos de la Administración del Estado deberán actualizar sus plataformas a tecnologías no obsoletas o carentes de soporte, así como generar medidas que permitan el rescate de los contenidos de formatos de archivo electrónicos que caigan en desuso. | D74: Ley 19880 | E74: =VLOOKUP(D74,Normativa!$A$3:$C$100,3,0) -> Ley | F74: Obligación | G74: Órganos de la Administración del Estado | H74: En virtud del principio de actualización, los órganos de la Administración del Estado deberán actualizar sus plataformas a tecnologías no obsoletas o carentes de soporte, así como generar medidas que permitan el rescate de los contenidos de formatos de archivo electrónicos que caigan en desuso. | I74: =IF(H74=H73,I73+1,1) -> 1 | J74: Los OAE que cumplen el principio de actualización deben actualizar sus plataformas a tecnologías no obsoletas o carentes de soporte, así como generar medidas que permitan el rescate de los contenidos de formatos de archivo electrónicos que caigan en desuso.
A75: FALSE | B75: En la tramitación de un procedimiento administrativo por medios electrónicos | C75: En la tramitación de los procedimientos administrativos por medios electrónicos se deberá cumplir con el principio de equivalencia funcional. En virtud del principio de equivalencia funcional, los órganos de la Administración del Estado deberán asegurar que los actos administrativos suscritos por medio de firma electrónica sean válidos y produzcan los mismos efectos que si se hubieren llevado a cabo en soporte de papel. | D75: Ley 19880 | E75: =VLOOKUP(D75,Normativa!$A$3:$C$100,3,0) -> Ley | F75: Obligación | G75: Órganos de la Administración del Estado | H75: El principio de equivalencia funcional consiste en que los actos administrativos suscritos por medio de firma electrónica serán válidos y producirán los mismos efectos que si se hubieren llevado a cabo en soporte de papel. | I75: =IF(H75=H74,I74+1,1) -> 1
A76: FALSE | B76: En la tramitación de un procedimiento administrativo por medios electrónicos | C76: En la tramitación de los procedimientos administrativos por medios electrónicos se deberá cumplir con el principio de fidelidad. En virtud del principio de fidelidad, los órganos de la Administración del Estado deberán asegurar que todas las actuaciones del procedimiento se registren y conserven íntegramente y en orden sucesivo en el expediente electrónico, el que garantizará su fidelidad, preservación y la reproducción de su contenido. | D76: Ley 19880 | E76: =VLOOKUP(D76,Normativa!$A$3:$C$100,3,0) -> Ley | F76: Obligación | G76: Órganos de la Administración del Estado | H76: El principio de fidelidad consiste en que todas las actuaciones del procedimiento se registrarán y conservarán íntegramente y en orden sucesivo en el expediente electrónico, el que garantizará su fidelidad, preservación y la reproducción de su contenido. | I76: =IF(H76=H75,I75+1,1) -> 1
A77: FALSE | B77: En la tramitación de un procedimiento administrativo por medios electrónicos | C77: En la tramitación de los procedimientos administrativos por medios electrónicos se deberá cumplir con el principio de interoperabilidad. En virtud del principio de interoperabilidad, los órganos de la Administración del Estado deben asegurar que los medios electrónicos sean capaces de interactuar y operar entre sí al interior de la Administración del Estado, a través de estándares abiertos que permitan una segura y expedita interconexión entre ellos. | D77: Ley 19880 | E77: =VLOOKUP(D77,Normativa!$A$3:$C$100,3,0) -> Ley | F77: Obligación | G77: Órganos de la Administración del Estado | H77: El principio de interoperabilidad consiste en que los medios electrónicos deben ser capaces de interactuar y operar entre sí al interior de la Administración del Estado, a través de estándares abiertos que permitan una segura y expedita interconexión entre ellos. | I77: =IF(H77=H76,I76+1,1) -> 1
A78: FALSE | B78: En la tramitación de un procedimiento administrativo por medios electrónicos | C78: En la tramitación de los procedimientos administrativos por medios electrónicos se deberá cumplir con el principio de cooperación. En virtud del principio de cooperación, los órganos de la Administración del Estado deben asegurar que cooperan efectivamente entre sí en la utilización de medios electrónicos. | D78: Ley 19880 | E78: =VLOOKUP(D78,Normativa!$A$3:$C$100,3,0) -> Ley | F78: Obligación | G78: Órganos de la Administración del Estado | H78: El principio de cooperación consiste en que los distintos órganos de la Administración del Estado deben cooperar efectivamente entre sí en la utilización de medios electrónicos. | I78: =IF(H78=H77,I77+1,1) -> 1
A79: FALSE | D79: Ley 19880 | E79: =VLOOKUP(D79,Normativa!$A$3:$C$100,3,0) -> Ley | I79: =IF(H79=H78,I78+1,1) -> 1
A80: FALSE | D80: Ley 19880 | E80: =VLOOKUP(D80,Normativa!$A$3:$C$100,3,0) -> Ley | H80: Artículo 17. Derechos de las personas. Las personas, en sus relaciones con la Administración, tienen derecho a: | I80: =IF(H80=H79,I79+1,1) -> 1
A81: FALSE | D81: Ley 19880 | E81: =VLOOKUP(D81,Normativa!$A$3:$C$100,3,0) -> Ley | I81: =IF(H81=H80,I80+1,1) -> 1
A82: FALSE | B82: En la tramitación de un procedimiento administrativo | C82: El órgano debe garantizar el derecho a las personas a conocer, en cualquier momento, el estado de la tramitación de los procedimientos en los que tengan la condición de interesados, y obtener copia autorizada de los documentos que rolan en el expediente y la devolución de los originales | D82: Ley 19880 | E82: =VLOOKUP(D82,Normativa!$A$3:$C$100,3,0) -> Ley | F82: Obligación | G82: Órganos de la Administración del Estado | H82: a) Conocer, en cualquier momento, el estado de la tramitación de los procedimientos en los que tengan la condición de interesados, y obtener copia autorizada de los documentos que rolan en el expediente y la devolución de los originales, salvo que por mandato legal o reglamentario éstos deban ser acompañados a los autos, a su costa. Constituye copia autorizada aquella generada por la plataforma electrónica donde se acceda al expediente electrónico, que cuente con un medio de verificación de su autenticidad; | I82: =IF(H82=H81,I81+1,1) -> 1
A83: FALSE | B83: En la tramitación de un procedimiento administrativo | C83: El órgano debe garantizar el derecho a las personas a identificar a las autoridades y al personal al servicio de la Administración, bajo cuya responsabilidad se tramite el procedimiento | D83: Ley 19880 | E83: =VLOOKUP(D83,Normativa!$A$3:$C$100,3,0) -> Ley | F83: Obligación | G83: Órganos de la Administración del Estado | H83: b) Identificar a las autoridades y al personal al servicio de la Administración, bajo cuya responsabilidad se tramiten los procedimientos; | I83: =IF(H83=H82,I82+1,1) -> 1
A84: FALSE | B84: En la tramitación de un procedimiento administrativo | C84: El órgano debe garantizar el derecho a las personas a acompañar documentos electrónicos, tales como copias digitalizadas de documentos en soporte de papel o documentos electrónicos en su origen, que no sean emitidos por los órganos de la Administración del Estado, en la medida que conste su autenticidad e integridad | D84: Ley 19880 | E84: =VLOOKUP(D84,Normativa!$A$3:$C$100,3,0) -> Ley | F84: Obligación | G84: Órganos de la Administración del Estado | H84: c) Acompañar documentos electrónicos, tales como copias digitalizadas de documentos en soporte de papel o documentos electrónicos en su origen, que no sean emitidos por los órganos de la Administración del Estado, en la medida que conste su autenticidad e integridad, salvo que por mandato legal o reglamentario éstos deban ser acompañados a los autos en soporte de papel, a su costa; | I84: =IF(H84=H83,I83+1,1) -> 1
A85: FALSE | B85: En la tramitación de un procedimiento administrativo | C85: El órgano que tuviere en su poder documentos que no correspondan al procedimiento o que emanen debe remitirlos a aquel órgano que está tramitando el procedimiento administrativo | D85: Ley 19880 | E85: =VLOOKUP(D85,Normativa!$A$3:$C$100,3,0) -> Ley | F85: Obligación | G85: Órganos de la Administración del Estado | H85: d) Eximirse de presentar documentos que no correspondan al procedimiento o que emanen y se encuentren en poder de cualquier órgano de la Administración del Estado. En este último caso, dichos documentos deberán ser remitidos por el órgano que los tuviere en su poder a aquel que estuviere tramitando el procedimiento administrativo; | I85: =IF(H85=H84,I84+1,1) -> 1
A86: FALSE | D86: Ley 19880 | E86: =VLOOKUP(D86,Normativa!$A$3:$C$100,3,0) -> Ley | H86: e) Acceder a los actos administrativos y sus documentos, en los términos previstos en la ley; | I86: =IF(H86=H85,I85+1,1) -> 1
A87: FALSE | D87: Ley 19880 | E87: =VLOOKUP(D87,Normativa!$A$3:$C$100,3,0) -> Ley | H87: f) Ser tratados con respeto y deferencia por las autoridades y funcionarios, que habrán de facilitarles el ejercicio de sus derechos y el cumplimiento de sus obligaciones. Los actos de instrucción que requieran la intervención de los interesados habrán de practicarse en la forma que resulte más cómoda para ellos y sea compatible, en la medida de lo posible, con sus obligaciones laborales o profesionales; | I87: =IF(H87=H86,I86+1,1) -> 1
A88: FALSE | D88: Ley 19880 | E88: =VLOOKUP(D88,Normativa!$A$3:$C$100,3,0) -> Ley | H88: g) Formular alegaciones y aportar documentos en cualquier fase del procedimiento anterior al trámite de audiencia, que deberán ser tenidos en cuenta por el órgano competente al redactar la propuesta de resolución; | I88: =IF(H88=H87,I87+1,1) -> 1
A89: FALSE | D89: Ley 19880 | E89: =VLOOKUP(D89,Normativa!$A$3:$C$100,3,0) -> Ley | H89: h) Exigir las responsabilidades de la Administración Pública y del personal a su servicio, cuando así corresponda legalmente; | I89: =IF(H89=H88,I88+1,1) -> 1
A90: FALSE | D90: Ley 19880 | E90: =VLOOKUP(D90,Normativa!$A$3:$C$100,3,0) -> Ley | H90: i) Obtener información acerca de los requisitos jurídicos o técnicos que las disposiciones vigentes impongan a los proyectos, actuaciones o solicitudes que se propongan realizar, e | I90: =IF(H90=H89,I89+1,1) -> 1
A91: FALSE | D91: Ley 19880 | E91: =VLOOKUP(D91,Normativa!$A$3:$C$100,3,0) -> Ley | H91: j) Cualesquiera otros que les reconozcan la Constitución y las leyes. | I91: =IF(H91=H90,I90+1,1) -> 1
A92: FALSE | D92: Ley 19880 | E92: =VLOOKUP(D92,Normativa!$A$3:$C$100,3,0) -> Ley | I92: =IF(H92=H91,I91+1,1) -> 1
A93: FALSE | D93: Ley 19880 | E93: =VLOOKUP(D93,Normativa!$A$3:$C$100,3,0) -> Ley | H93: CAPITULO II | I93: =IF(H93=H92,I92+1,1) -> 1
A94: FALSE | D94: Ley 19880 | E94: =VLOOKUP(D94,Normativa!$A$3:$C$100,3,0) -> Ley | I94: =IF(H94=H93,I93+1,1) -> 1
A95: FALSE | D95: Ley 19880 | E95: =VLOOKUP(D95,Normativa!$A$3:$C$100,3,0) -> Ley | H95: El Procedimiento Administrativo | I95: =IF(H95=H94,I94+1,1) -> 1
A96: FALSE | D96: Ley 19880 | E96: =VLOOKUP(D96,Normativa!$A$3:$C$100,3,0) -> Ley | I96: =IF(H96=H95,I95+1,1) -> 1
A97: FALSE | D97: Ley 19880 | E97: =VLOOKUP(D97,Normativa!$A$3:$C$100,3,0) -> Ley | H97: Párrafo 1º | I97: =IF(H97=H96,I96+1,1) -> 1
A98: FALSE | D98: Ley 19880 | E98: =VLOOKUP(D98,Normativa!$A$3:$C$100,3,0) -> Ley | I98: =IF(H98=H97,I97+1,1) -> 1
A99: FALSE | D99: Ley 19880 | E99: =VLOOKUP(D99,Normativa!$A$3:$C$100,3,0) -> Ley | H99: Normas básicas | I99: =IF(H99=H98,I98+1,1) -> 1
A100: FALSE | D100: Ley 19880 | E100: =VLOOKUP(D100,Normativa!$A$3:$C$100,3,0) -> Ley | H100: Artículo 18. Definición. El procedimiento administrativo es una sucesión de actos trámite vinculados entre sí, emanados de la Administración y, en su caso, de particulares interesados, que tiene por finalidad producir un acto administrativo terminal. | I100: =IF(H100=H99,I99+1,1) -> 1
A101: FALSE | D101: Ley 19880 | E101: =VLOOKUP(D101,Normativa!$A$3:$C$100,3,0) -> Ley | H101: El procedimiento administrativo consta de las siguientes etapas: iniciación, instrucción y finalización. | I101: =IF(H101=H100,I100+1,1) -> 1
A102: FALSE | D102: Ley 19880 | E102: =VLOOKUP(D102,Normativa!$A$3:$C$100,3,0) -> Ley | H102: Todo el procedimiento administrativo deberá constar en un expediente electrónico, salvo las excepciones contempladas en la ley, en el que se asentarán los documentos presentados por los interesados, por terceros y por otros órganos públicos, con expresión de la fecha y hora de su recepción, respetando su orden de ingreso. Asimismo, se incorporarán las actuaciones y los documentos y resoluciones que el órgano administrativo remita a los interesados, a terceros o a otros órganos públicos y las notificaciones y comunicaciones a que éstas den lugar, con expresión de la fecha y hora de su envío, en estricto orden de ocurrencia o egreso. | I102: =IF(H102=H101,I101+1,1) -> 1
...

Sheet Relaciones
A3: Norma Técnica de Interoperabilidad 2023-12 | B3: Decreto MINSEGPRES 2021-4

Sheet Hoja 5
B1: Ideas
B2: Todas las entradas enviadas a esta fase
B3: Búsqueda
B4: Búsqueda
B5: 29 resultados de búsqueda cargados.
B7: Más reciente
B9: Temas
B11: Lista
B13: Mapa
B14: Comentarios Estrategia Gestión de Datos Mayo 2023
A16: 45068 | B16: Patricio Véjar•hace 5 días Se ve una estrategia bastante integral y acorde con los desafíos de implementación que contempla dar un salto cualitativo y cuantitativo necesario cumplir con el objetivo de lograr contar con un gobierno digital en el plazo estipulado.Solo algunos comentarios:2. Contexto.En este capítulo se hecha de menos un diagnóstico del nivel de conocimiento digital de la población – en última instancia propietarios de los datos que se busca gestionar -. La mayoría de la población carece de una adecuada educación digital que le permita reconocer la importancia de entregar información veraz y pertinente. Por esta razón pareciera razonable incorporar procesos educativos en la estrategia. Adicionalmente, la población ha mostrado tener un elevado nivel de desconfianza en las instituciones lo que conllevaría dificultades para contar con la participación colaborativa de los usuarios y las usuarias de los servicios estatales en los diversos nivelas, para asegurar la calidad de los datos a recolectar.3.4.3.1. Modelo federado de datosSeñala el primer párrafo que “cada organismo es dueño y responsable de sus datos”. Esto no sería correcto dado que la mayoría de los datos almacenados serían propiedad de los usuarios y las usuarias de los organismos lo que es reconocido en otros acápites del documento. Para ser coherentes cada organismo debería reconocerse como mero administrador de los datos en su poder.En el siguiente párrafo señala: “un organismo que actuará como &lt;&lt;Proveedor&gt;&gt; de datos, y otro como &lt;&lt;Consumidor&gt;&gt;. En estricto rigor con la interoperabilidad debería existir una relación bidireccional entre los distintos puntos de recolección y almacenamiento de datos más aún si se está trabajando con plataformas descentralizadas.En el párrafo posterior donde lista los distintos servicios que se dispondrán para interoperar se menciona el Directorio de Datos asignándole la exposición de la “oferta de datos” de la Administración del Estado. En mi opinión la forma más pertinente para mencionar la tarea del Directorio de Datos es “exposición de la disponibilidad de datos”.En relación al Catálogo de Servicios, no pareciera pertinente asignarle la tares de “descubrimiento de servicios” dado el carácter descentralizado del sistema en su conjunto y el carácter autónomo de los elementos integrantes de la Red de Interoperabilidad.Finalmente en el párrafo subsiguiente y en relación a “la actualización constante de los conjuntos de datos” se hecha de menos la presencia de estándares de calidad y pertinencia de los datos, y estos estándares deberían, a su vez, generar procedimientos de validación y procesos de optimización de la calidad de los datos. Actualizar conjuntos de datos de baja calidad incrementará las imprecisiones sistémicas existentes.
B17: Total votos a favor: 1, total votos en contra: 0
B18: 0
B19: 0 comentarios
B20: PROPUESTA
B21: Fortalecimiento de la coordinación
B23: Michel Figueroa Mardones•hace 5 días La estrategia de gestión de datos representa un esfuerzo global por darle articulación a los esfuerzo de producción, almacenamiento y difusión de los datos gubernamentales. Se valora positivamente la intensión de asumir una posición ante las problemáticas de la gestión de datos.Aunque es un primer esfuerzo por parte del ejecutivo, es necesario extender la aplicación de este tipo de estrategia a los otros poderes del Estado, buscando facilitar así la interacción y experiencia ciudadana con las diferentes manifestaciones estatales.Los mecanismos de gobernanza interactiva, propios de la estructuras múltinivel como la que se propone, requiere una capacidad de coordinación y liderazgo que no se ha visibilizado en el pasado en esta ni otras materias y que puede ser el principal obstáculo a la hora de implementar la estrategia en cuestión. Parece dable entonces, poner acento e las facultades de la autoridad de datos para poder llevar a cabo los esfuerzos de coordinación y de ser posible simplificar la estructura de gobernanza de datos.
B24: Total votos a favor: 1, total votos en contra: 0
B25: 0
B26: 0 comentarios
B27: PROPUESTA
B28: Comentarios y propuestas para la Estrategia de Gestión de Datos del Estado
B30: Emilio Muñoz•hace 6 días Sobre el alcance de la Estrategia de Gestión de DatosEn primer lugar, el texto menciona que "la protección de los derechos de las personas en el tratamiento de sus datos personales es materia de legislación y queda por definir la instancia a cargo de supervisar el cumplimiento de dicha normativa". Sin embargo, esta afirmación no es correcta porque la nueva Ley de Protección de Datos ya está próxima a ser promulgada y efectivamente contempla la creación de una agencia encargada de supervisar el cumplimiento de la normativa. Además, es conocido que la nueva ley será similar al Reglamento General de Protección de Datos de la Unión Europea. No dejemos pasar la oportunidad para promover la privacidad y la protección de datos de las personas en la Estrategia. Se puede hacer potenciando las línea de acción "Seguridad y protección de la privacidad" que ya existe en la hoja de ruta y que está sido poco desarrollada.Otro aspecto es que el documento resalta la importancia del Portal de Datos Abiertos. Sin embargo, es relevante tener en cuenta que este tipo de portales se basa en el paradigma de Gobierno Abierto o Estado Abierto, un concepto que no se menciona en la Estrategia y que podría considerarse como una línea de acción adicional. Este tipo de portales son el resultado de un proceso de apertura dentro de una organización, que requiere un esfuerzo previo para garantizar la pertinencia y calidad de los datos que se compartirán con el público. En este sentido, dicho esfuerzo previo se asemeja a las actividades propuestas en la estrategia de gestión de datos.En la misma línea, se menciona la generación de iniciativas de inteligencia artificial basadas en datos. Sin embargo, estas también podrían considerarse como productos, ya que requieren que las instituciones, sectores o temáticas tengan un cierto nivel de madurez en la gestión de datos. Las iniciativas de inteligencia artificial no se mencionan en el roadmap, solo se abordan como parte de las funciones del CDO.Otro aspecto relacionado con el alcance es la inclusión de otras organizaciones públicas, como municipios, empresas públicas, poderes del Estado, organizaciones autónomas, entre otras. Aunque la estrategia indica que se aplicará a todos los órganos de la Administración del Estado, sería importante aclarar si se considerarán las organizaciones mencionadas.Sobre el Ciclo de valor en la gestión de datosDado que los objetivos de la gestión de datos pasan por garantizar su calidad, en esta sección se sugiere incluir algunas cuestiones conceptuales, por ejemplo definir qué se entiende por "dato" según la presente Estrategia, así como enumerar los tipos o categorías de datos que el Estado pretende gobernar a través de la misma.Como sugerencia, en general se podría utilizar el término "tratamiento" para agrupar el conjunto de operaciones que se realizan sobre los datos, ya que es el término preferido en las normativas.Además, se recomienda revisar la referencia a las etapas respecto de la figura, por ejemplo nombra las etapas como N°3, N°4, pero la imagen no tiene las etapas numeradas. Se sugiere tambien aumentar el tamaño del texto.Sobre los Niveles de la EstrategiaNivel 1 - Nivel OrganizaciónEn mi opinión, los elementos proporcionados a este nivel serán fundamentales para una rápida adopción del marco de trabajo y el éxito de la estrategia de gestión de datos del Estado. En este sentido, la estrategia debería proponer mecanismos para institucionalizar la gobernanza de datos con la menor fricción posible. Dentro de las organizaciones, existen diversas unidades y partes interesadas que manejan datos desde diferentes perspectivas, como los departamentos de TIC, los departamentos de seguridad de la información, el área jurídica o de cumplimiento normativo, así como las propias unidades de negocio que utilizan y evalúan el valor de cada dato tratado. De hecho, actualmente son las unidades de negocio donde se están instalando las capacidades de análisis de datos o ciencia de datos.En razón de lo anterior, se sugiere proponer cómo la estrategia será adoptada por la organización y cómo se "conversará" con las unidades y partes interesadas mencionadas anteriormente.Esta interacción tomará mayor relevancia con la promulgación y puesta en marcha de las leyes de Ciberseguridad e Infraestructura Crítica, así como la actualización de la Ley de Protección de Datos, ya que es muy probable que involucren actividades similares a las que propone TOGAF y DAMA, como el levantamiento de procesos e identificación de activos de información al interior de la organización.En la misma línea, considero importante establecer el alcance y la jerarquía del rol del Encargado de Gestión de Datos. ¿Este rol estará por encima de las unidades y partes interesadas mencionadas anteriormente? Es necesario que este rol cuente con la autoridad necesaria para impulsar el avance de la estrategia; de lo contrario, el nivel estratégico (Gobierno Digital) podría ser requerido frecuentemente para intervenir con los jefes de servicio cuando surjan controversias con la implementación de la estrategia.Una idea para simplificar y evitar la creación de nuevos cargos o unidades es que la estrategia proporcione previamente las pautas que ayuden a identificar la unidad o la parte interesada más idónea para asumir el rol de Encargado de Gestión de Datos en la organización. Por supuesto, estas pautas deben considerar la complejidad y el propósito de la organización,Por último, aunque se menciona brevemente que la estrategia buscará en principio consolidar únicamente el dominio de Arquitectura de Datos, es importante tener en cuenta que abordar la implementación de dicho dominio requiere un gran esfuerzo previo por parte de la organización y del encargado para generar los insumos necesarios. Consultar el punto 9.2.3 del framework en https://pubs.opengroup.org/architecture/togaf9-doc/arch/Nivel 2 - Sectores o TemáticasSe sugiere que la estrategia establezca desde el principio los sectores y temáticas, las organizaciones participantes y una priorización basada en la complejidad y criticidad para los intereses del país. Algunos sectores son evidentes, como salud o seguridad pública. De esta manera, se facilitará la coordinación entre las organizaciones, definiendo los sectores y temáticas macro desde el principio, al tiempo que se conserva la libertad de las instituciones para agruparse por iniciativa propia. Además, se menciona que las instituciones que converjan en cada sector o temática conformarán hubs para definir sus estándares, semántica, codificaciones, clasificaciones y servicios compartidos. Sin embargo se recomienda que la División realice un levantamiento sobre cada una de estas materias y provea un set de definiciones iniciales, de modo que los hubs construyan a partir de una base previamente validada por la estrategia, ya que por lo demás las definiciones de los sectores y temáticas eventualmente también tendrán que “conversar” entre sí.En general, considero que el propósito articulador de este nivel debería comenzar por analizar lo que se está haciendo actualmente dentro de cada sector, tomando como insumo el levantamiento inicial entregado por Gobierno Digital, para luego identificar las brechas existentes y comenzar a trabajar desde ahí. En complemento, las mesas sectoriales y temáticas también deberían designar a un representante que interactúe con Gobierno Digital y con otras instancias como el Comité Estratégico cuando corresponda.En este nivel, la estrategia también debería incluir la participación o asesoría de otros actores transversales a nivel técnico, como la academia, la ciudadanía, el sector privado y entidades especializadas como el CLPT y las futuras agencias de ciberseguridad e infraestructura crítica y la agencia de protección de datos personales.Finalmente, se menciona la creación de un centro de datos, pero no queda claro si se refiere a infraestructura o a un concepto. Se sugiere que se defina claramente. En caso de que se refiera a infraestructura, se sugiere no incluirlo en la estrategia, ya que es un elemento más técnico y podría generar expectativas en el sector privado que la estrategia deberá abordar eventualmente. No obstante, la estrategia debería expresar la voluntad de buscar la colaboración público-privada y así generar sinergias que ayuden a alcanzar los objetivos y que beneficien a ambas partes.Nivel 3 - EstadoEn este nivel se le da amplia cobertura y relevancia a que la división proveerá los servicios compartidos de interoperabilidad (los Nodos o PISEE 2.0) y el Portal de Datos Abiertos. Sin embargo, a pesar de ser componentes importantes, el papel del Estado en este caso debería centrarse en actuar como un facilitador, entregando las pautas y definiciones iniciales y los instrumentos habilitantes que se utilizarán durante la ejecución de la estrategia.Las definiciones iniciales incluyen los elementos mencionados en los niveles anteriores, por ejemplo los lineamientos para identificar al encargado de gestión de datos en las organizaciones, los lineamientos tácticos para adoptar los Nodos y el levantamiento inicial de estándares, semánticas, codificaciones, clasificaciones, maestros de datos y servicios compartidos que se utilizarán en forma transversal y en los hubs sectoriales y temáticos definidos.En la misma línea, en la sección donde se describe el modelo federado, se mencionan una serie de herramientas que serían provistas por Gobierno Digital a las organizaciones (directorio de datos, catálogo de servicios, esquemas y gestor de acuerdos), sin embargo estas herramientas no están descritas en ninguna parte del documento ni tampoco se indica si ya existen o se desarrollarán. Sería ideal que Gobierno Digital las facilite desde el principio, al igual que las definiciones iniciales.Respecto a los instrumentos habilitantes, Gobierno Digital podría liderar el despliegue de actos administrativos que generen impulso en las instituciones, como resoluciones para mandatar el cumplimiento de la estrategia o incluso - por qué no - un instructivo presidencial con ese fin. Considero que se desarrolla poco una “ambición” normativa institucional y a nivel de políticas públicas, que es lo que debiese buscar la estrategia, que aspira a tener un Estado basado en datos (Data-driven) y materializar grandes cambios en la cultura y gestión de las organizaciones. Por ejemplo, para lograr estas grandes transformaciones parece muy atractivo promover el uso de la Arquitectura Empresarial, pero la sola implementación de la gobernanza de datos no es suficiente, ya que la Arquitectura Empresarial interviene prácticamente todo en la organización: procesos, estructuras, tecnologías, etc. por lo tanto podría durar muchos años. Aquí la Estrategia pódría decir expresamente que el Gobierno de Datos será el punto de partida y así se establece una expectativa sin dejar de lado la aspiración de llegar al objetivo mayor (Estado y políticas publicas basadas en datos).Otro instrumento facilitador que Gobierno Digital podría proporcionar es la gestión para asígnar recursos a organizaciones con menor madurez o capacidades instaladas, como municipios y servicios pequeños.Por último, otra recomendación es que la estrategia incluya indicadores de alto nivel y plazos más concretos, de modo que se pueda llevar a cabo una adecuada rendición de cuentas y medir el progreso, siendo coherente con el roadmap.Sobre el Modelo FederadoCreo que esta toda esta sección debería explicarse dentro de la estrategia a nivel de organizaciones, ya que el modelo federado mediantes los Nodos es lo que materializa el proceso de gestión de los datos en la organización.El Nodo es un habilitador muy potente que facilita el intercambio de datos desde organizaciones, sin embargo hay que considerar que dentro una institución pueden haber muchos sistemas, poca gobernanza sobre ellos, externalizaciones, tecnologías dispares, obsolescencia, etc. Por lo tanto la estrategia debería proporcionar, por ejemplo, los lineamientos tácticos y operativos de cómo implementar uno o varios Nodos dentro de una organización en funcion a las arquitecturas existentes.Adicionalmente, sugiero cambiar figura 6 por un esquema que refleje el funcionamiento del Nodo y el modelo federado como un flujo, para mayor claridad.Sobre el Director de Gobernanza de Datos del Estado (Chief Data Oficer)Se indica que su objetivo es impulsar las iniciativas de la hoja de ruta, pero al ser una función ejecutiva, su rol debería incluir también la responsabilidad de garantizar el cumplimiento de la hoja de ruta / roadmap.En general, las responsabilidades del cargo se asemejan más a las de un coordinador. Además, algunas actividades parecen estar relacionadas con las responsabilidades de Gobierno Digital como entidad, por ejemplo, "Proporcionar lineamientos técnicos". Sugiero incluir dentro de los objetivos del cargo la búsqueda de oportunidades para utilizar datos en la resolución de problemáticas públicas y en el diseño de políticas públicas basadas en evidencia.Sobre el Comité Estratégico de Datos del EstadoComo propuesta, sugiero incluir la participación de representantes de las mesas sectoriales o temáticas. De hecho, es posible que en la práctica, estos representantes sectoriales coincidan con las instituciones estratégicas que menciona el documento.Sobre Plataforma de seguimiento para la implementación de la EstrategiaSe sugiere agregar una descripción más detallada, ya que no queda claro si el portal estará orientado a la ciudadanía, a las instituciones o si será una herramienta de control de gestión para la división, o si cumplirá todas estas funciones.En esta sección es el único lugar donde se menciona que la estrategia tendrá grados de cumplimiento y plazos definidos. En línea con la recomendación en párrafos anteriores, sería ideal que la descripción de esta plataforma sea coherente con los indicadores de alto nivel y los tiempos del roadmap.Finalmente, en el esquema de la figura 8 aparece otra herramienta de gestión aparte de la plataforma de seguimiento, que es el Directorio de Datos, sin embargo, no está descrito en la estrategia y solo se nombra una vez. También es un concepto que sería interesante saber qué es, por eso se sugiere incluir una descripción.Sobre la hoja de rutaRecomendaría darle más relevancia a las Líneas de Acción, ya que son ejes temáticos basados en las brechas que se identificaron para el sector público chileno, según lo que consta en la introducción. Las líneas de acción se podrían dejar como el punto 3.4 antes la sección Niveles de la Estrategia.Sobre las iniciativas del roadmapSugiero generar una iniciativa orientada a instalar a los encargados de datos en las instituciones, ya que esta tarea requiere más tiempo y esfuerzo de coordinación que la conformación de comités y mesas sectoriales, por ejemplo.En la iniciativa sobre la creación de una Norma Técnica de Datos Abiertos, sugiero ampliar su alcance para los datos en general (Norma Técnica de Datos), ya que esto ayudaría a la estandarización y proporcionaría un mayor respaldo a las definiciones iniciales sobre semántica, codificación, clasificación y servicios compartidos de la estrategia. Posteriormente, dentro de la misma norma, se podrían incluir los lineamientos sobre el tratamiento de los datos que pueden ser abiertos. Otra idea sería asociar esta norma con la de Interoperabilidad de la Ley de Transformación Digital.En general, se sugiere dar mayor claridad a los plazos de las iniciativas del roadmap, evitando usar términos relativos como corto y largo plazo. Además, algunas iniciativas se entienden más como actividades que hitos y quizás se podrían agrupar o replantear con un nivel de abstracción similar. Finalmente sería conveniente visualizar el roadmap como una línea de tiempo para ayudar a su comprensión.######## FIN ########Muchas gracias por el espacio de participación.Como nota aparte: Puede que el sistema citizenlab.co sobre el cual está hecho participacion.digital.gob.cl tenga posibilidad de integrarse con ClaveÚnica, para autenticarse con este medio en lugar de usar conectores sociales. ClaveÚnica utiliza el estándar OpenID Connect en su implementación.
B31: Total votos a favor: 3, total votos en contra: 0
B32: 0
B33: 0 comentarios
B34: PROPUESTA
B35: Opinión del GobLab Universidad Adolfo Ibáñez
B36: Maria Paz Hermosilla•hace 1 semana Remitimos la opinión del GobLab, laboratorio de innovación pública de la Escuela de Gobierno de la Universidad Adolfo Ibáñez. Comentarios generales: La propuesta nos parece buena general, es un documento que tiene bastante reflexión y da la impresión de que está basado en experiencias internacionales serias. Un tema notoriamente ausente de la Estrategia de Gestión de Datos es la necesidad de integración de datos del Estado para mejorar el diseño y evaluación de políticas públicas. En diversas secciones del documento se habla del “intercambio y utilización de los datos” o de “gestión e intercambio” pero no se menciona la necesidad de integración. (pg. 4, 7, 8, 10, 21, 24) En Chile, la discusión y propuestas para el acceso a datos integrados del Estado lleva varios años. En el 2006, un comité del INE plantea a la Comisión Nacional de Estadísticas la necesidad de generar un sistema de acceso a los microdatos públicos. En 2017, el Informe de la Comisión de Modernización del Estado del CEP propone directamente la creación de una infraestructura de datos integrada, citando al caso neozelandés. También, el Estudio de Uso Intensivo de Datos del Ministerio de Hacienda, plantea el desarrollo de un gobierno basado en datos, con la generación de una plataforma de producción, recolección y disponibilización de datos. El Ministerio de Desarrollo Social y Familia realiza desde 2020 un piloto de acceso al Registro de Información Social, completando 6 convocatorias a la fecha con un total de 27 proyectos aceptados. En 2022, la Comisión Nacional de Evaluación y Productividad recomendó solicitar al INE “implementar un sistema integrado de datos administrativos a partir de información generada o recolectada por los diversos órganos públicos en el marco de sus competencias, con el objeto de poner a disposición dicha información a fin de evaluar y diseñar políticas públicas.” Ese mismo año, la Universidad Adolfo Ibáñez, la Pontificia Universidad Católica de Chile, la Universidad de Chile y la Universidad Diego Portales firman un convenio de colaboración a 5 años para conformar un consorcio cuyo objetivo es impulsar la creación de una Infraestructura Integrada y Segura de Datos para Chile, materializando una colaboración que se inició a finales de 2019 con la organización de una visita público privada a conocer la infraestructura integrada de datos de Nueva Zelandia. Muchos países tienen bases de datos integradas, que contienen datos personales y sensibles desidentificados, pero que se ofrece un acceso seguro a dichas bases de datos ya que no se pueden abrir por el riesgo de re-identificación. Ver estudios Biblioteca del Congreso Nacional: UK: https://www.bcn.cl/asesoriasparlamentarias/detalle_documento.html?id=79554 Dinamarca: https://www.bcn.cl/asesoriasparlamentarias/detalle_documento.html?id=79485 NZ: https://www.bcn.cl/asesoriasparlamentarias/detalle_documento.html?id=79359 Noruega: https://www.bcn.cl/asesoriasparlamentarias/detalle_documento.html?id=79553 Suecia: https://www.bcn.cl/asesoriasparlamentarias/detalle_documento.html?id=79404 Canadá: https://www.bcn.cl/asesoriasparlamentarias/detalle_documento.html?id=79433 Una estrategia debería establecer claramente un conjunto de directrices o principios que ayuden a tomar decisiones eficientes, coherentes y alineadas hacia un objetivo. En este sentido el documento resulta difuso. Falta que esas directrices o declaraciones estratégicas estén más explícitas. Por ejemplo: "foco en el trabajo colaborativo", "generación de conocimiento respecto de los modelos de datos", "establecimiento de mecanismos flexibles de conexión y transferencias". Sobre la experiencia de participación: El ingreso a la consulta pública debería haber sido con clave única gubernamental, y en el caso se usó la conexión a Facebook y Google. El ingreso a través de estas plataformas privadas dan paso a que estos servicios respondan por ti y administren tu cuenta.No se explica detalladamente a lo que el servicio que facilita el acceso finalmente accede. Mas información aqui: https://www.aepd.es/es/prensa-y-comunicacion/blog/riesgos-privacidad-iniciar-sesion-cuentas-rrss-otras-aplicaciones Sugerimos numerar las páginas del documento final. IntroducciónSugerimos agregar a la introducción una mención al mal uso que se puede dar a los datos y el efecto que esto puede tener en los derechos de las personas.Contexto: La estrategia podría quedar rápidamente desactualizada con las referencias que en materia de protección de datos se hacen al Consejo para la Transparencia. La entidad de protección de datos ya está definida en el proyecto de ley y en estado en que encuentra el proyecto no es algo que hoy pudiera cambiar. Es importante remarcar que la ley de protección de datos personales abarca una parte de los datos que son útiles, el gobierno de datos los considera a todos. Esta sección no menciona la importancia del acceso a datos integrados (administrativos y de encuestas) para diseñar y evaluar políticas públicas. En el párrafo final de la página 6, sugerimos mencionar el porcentaje de adopción de la PISEE 1, a partir de un estudio realizado en 2017, es un dato ilustrativo. En las menciones a la apertura de datos, se deja fuera la importancia del acceso a datos de manera segura, porque no todos los datos pueden ser abiertos. 3.Estrategia de gestión de datos 3.2. Alcance de la estrategiaEn la oración “Las oportunidades que la Inteligencia Artificial ofrece son también extensivas a las organizaciones del sector público, como lo demuestra el uso de algoritmos para identificar necesidades de los usuarios, o para asignar de manera más precisa beneficios sociales” se podría incluir una nota al pie del Repositorio Algoritmos Públicos de la UAI https://www.algoritmospublicos.cl/ Considerando que el principio es que los datos puedan ser usados de las formas más diversas, nos parece esencial el diseño y evolución de mecanismos para la calidad, completitud y coherencia de la información, habida cuenta que ninguna de las 3 dimensiones puede ser garantizada. 3.3 Ciclo de vidaSugerimos revisar las traducciones de las figura 1. (Ej. “Colectar”, “Interesados Públicos”) 3.4. Niveles de la estrategia: La definición de la estrategia debiera hacer abstracción del juicio de lo logrado o lo pendiente. Sin duda es importante y quizás debe ir en un anexo, pero no es parte de la estrategia. Lo logrado puede condicionar a la estrategia, o más bien condiciona su punto de partida, pero no es parte sustantiva de la estrategia misma.3.4.1 Estrategia a nivel de organismos(pg. 13) Se echa de menos alguna referencia a la gobernanza en el marco de la arquitectura empresarial y en particular de la gobernanza de procesos. Este tema tampoco está desarrollado en las guías relativas a procesos y que son parte relevante para el modelamiento y mejora de los procedimientos administrativos.(pg 14) Considerando que DAMA es un marco de referencia bastante amplio y puede resultar complejo para las organizaciones de menor tamaño, sería interesante considerar 2 versiones: un DAMA base (con foco en gobernanza) y un DAMA avanzado (que incluye las prácticas) 4. Gobernanza:Promover el fortalecimiento de las contrapartes siempre es una buena idea. El Estado debe tener cargos ejecutivos, como el Chief Data Officer, los cuales tienen un tremendo rol evangelizador, pero además es necesario que hay contrapartes técnicas y ejecutivas en la mayor parte de las dependencias del Estado, a nivel Regional y en los demás sectores, i.e. en el sector privado (ej fortalecer contrapartes en Sofofa y similares), y en la sociedad civil organizada (promover observatorios privados y académicos, etc.). El énfasis acá es la colaboración y el desarrollo de capacidades.4.2 Gobernanza a nivel de sectores Los Comités Temático-Sectoriales de Datos son claves también para desarrollar una gobernanza común al sector que permita permear desde allí hacia las organismos, esto además facilita el trabajo de las definiciones de datos en forma conjunta y no individual que tiene el riesgo de no resultar alineado al sector. 4.3. Gobernanza a nivel estratégicoLa gobernanza a nivel estratégico debería además ser responsable de capacitar a los comités sectoriales y a los organismos, así como transferir buenas prácticas.4.3.2. Comité Estratégico de Datos del EstadoSugerimos incorporar a la academia en la estrategia con mayor visibilidad. p.ej. en el Comité Estratégico de Datos del Estado. Hacer concursos con ellos, incorporar memoristas, etc.5. Hoja de Ruta. La hoja de ruta tiene 5 ejes, sin embargo el eje de privacidad y seguridad tiene solo una iniciativa asociada, que tradicionalmente ha estado vinculada a las labores propias de Agencias de Protección de Datos. Además una sola acción pareciera insuficiente si se considera un “eje”. Los conceptos de privacidad, seguridad y resiliencia no aparecen suficientemente destacados. En la hoja de ruta faltan los temas de capacidades, colaboración, etc. Está presente fundamentalmente la dimensión técnica. Abordar esta dimensión el mayor pendiente que tiene la estrategia propuesta. Hace falta una línea de acción que tenga que ver con el uso de los datos para análisis y ciencia de datos que se encargue de generar valor público con los datos.
B37: Total votos a favor: 4, total votos en contra: 0
B38: 0
B39: 0 comentarios
B40: PROPUESTA
B41: Mecanismos de acceso a la comunidad a las distintas fases de generación de datos
B42: Mauricio Fuentes Alburquenque•hace 1 semana El camino que recorren los datos desde su generación en los distintos organismos hasta que se encuentran disponibles (ciclo de valor de los datos) hace que exista un alto riesgo de que éstos sufran alteraciones por errores de diverso tipo (digitación, traspaso, codificación, consolidación, respaldo, etc.).En este sentido, además de contar con informes y memorias sobre el procesamiento de la información en todas sus etapas, sería un tremendo aporte, en mi opinión, si la Estrategia creara mecanismos que permitieran a la comunidad en general (sociedad civil, instituciones, personas naturales, etc.), externa al Estado, poder tener acceso a los datos en cada una de dichas fases. Lo anterior, por supuesto, resguardando los derechos de las personas en cuanto a su privacidad e información sensible y no alterando el adecuado funcionamiento de los organismos públicos.
B43: Total votos a favor: 1, total votos en contra: 0
B44: 0
B45: 0 comentarios
B46: PROPUESTA
B47: Comentarios AWS
B49: Carmina Hernandez•hace 1 semana · En general, valoramos el objetivo de la estrategia presentada, en línea con las recomendaciones de la OCDE y otras organizaciones internacionales, además de las prácticas de los países más avanzados en la materia. · Se aprecia la realización de acciones para optimizar la gestión de los datos a nivel de organismos públicos, sectores o temáticas de política pública y en la administración del Estado en su totalidad. o A nivel sectorial, se valora la promoción de la participación de actores del sector empresarial, académicos, desarrolladores, emprendedores y otros, para generar espacios de interacción entre los organismos del Estado y agentes externos. · En cuanto a la hoja de ruta y su segunda línea de acción, infraestructura y tecnología, proponemos que para preparar el soporte tecnológico adecuado para la gestión e integración de datos en el Estado se considere la adopción de tecnología basada en la nube. · Por último, coincidimos con la tercera línea de acción, ecosistema de datos, la cual supone la creación y fortalecimiento de un ecosistema de actores que permita la colaboración entre agentes del sector público y entre el sector público y privado, en torno al uso y reutilización de los datos gubernamentales. o En este sentido, manifestamos nuestra disposición a colaborar en el proceso de implementación de esta estrategia y para ello sugerimos poner énfasis en la formación y capacitación de funcionarios y funcionarias del sector público. o Como compañía realizamos diversas capacitaciones en tecnología en el sector público, y estamos explorando opciones de sumar estos procesos a la carrera funcionaria. Uno de nuestros programas actuales, Government Executive Education (que realizamos en enero de este año en Chile), está dirigido a todos los funcionarios del sector público y tiene foco en transformación digital, modernización del Estado e innovación pública.
B50: Total votos a favor: 1, total votos en contra: 0
B51: 0
B52: 0 comentarios
B53: PROPUESTA
B54: Evaluación de calidad y transformación de RRAA como parte de la estrategia de GD
B56: Ester Díaz•hace 1 semana En el marco del alcance del documento y en específico a los niveles de la estrategia o más bien "las" estrategias que deberían desarrollarse para una adecuada gestión de datos. Se ve necesario hacer una bajada directa a la realidad nacional, principalmente cuando tomamos referentes e iniciativas internacionales (como DAMA por ejemplo). En ese punto, el documento no aborda, ni menciona, que gran parte de la información que generan las instituciones del estado son Registros Administrativos (RRAA), donde la calidad de los datos es desconocida y que se deberán plantear estrategias de transformación para garantizar su usabilidad.Para ello existen iniciativas nacionales e instancias regionales (LATAM) que abordan o definen "estrategias" e incluso herramientas de evaluación de datos provenientes de RRAA, por ejemplo Grupo de Trabajo de CEA CEPAL (Grupo de Trabajo Herramienta de Evaluación de la Calidad de los Registros Administrativos / Quality Assessment Tool for Administrative Records (cepal.org)).Cuando el documento define que "cada organismo debe constituirse en una fuente confiable de datos en su ámbito de acción, cumpliendo estándares de seguridad, documentación y calidad de los datos, compatibilizando adecuadamente la debida protección de los datos con su uso y eventual apertura".Se debería incluir, por ejemplo, que hablamos de la calidad de los datos provenientes de RRAA y otras fuentes administrativas, donde la definición de la estrategia de gestión de los datos debe ser complementada con herramientas de evaluación y estrategias de transformación, maximizando su aprovechamiento interno y para la producción de estadísticas oficiales.
B57: Total votos a favor: 1, total votos en contra: 0
B58: 0
B59: 0 comentarios
B60: PROPUESTA
B61: Propuestas Enlaces - Mineduc
B62: José Gorrini•hace 1 semana Nos parece una buena iniciativa, que crea un marco general, nos permitimos hacer las siguientes surgencias: Nos parece que es deseable que se realice recomendaciones técnicas de gestión de datos al interior de cada grupo sectorial y a nivel de unidades. Creemos que no basta solo centrarse en orientaciones interinstitucionales y solo de interoperabilidad. Las principales fallas de valorización de los datos creemos que se dan al interior de las instituciones. Creemos que debe fomentarse un trabajo fundacional, por ejemplo, generar catálogos de datos y formación en DAMA y Togaf para los funcionarios involucrados. Otro habilitador que nos parece ausente es que al momento de reducir el uso de papeles no se fomenta la obtención de firma digital avanzada por parte de todos los actores públicos y los colaboradores del estado. Por ejemplo, creemos que para las instituciones del estado central debieran estar obligadas a usar firma digital avanzada y las instituciones de nivel regional, provincial y comunal debieran progresivamente converger a lo mismo. Finalmente creemos que el estado debiera facilitar la obtención de firmas digitales avanzadas a los colaboradores del estado como son sostenedores y administradores de establecimientos subvencionados, que deben firmar convenios con el estado. Debiera considerarse sanitización de documentos públicos que incluyen datos personales o sensibles. Debiera fomentarse digitalizar documentos legales (REX, DEX, etc.) sobre todo aquellos en provincias. Se podría hacer evaluaciones de seguridad centralizadas de los sectoriales y de instituciones (White hat hacking).
B63: Total votos a favor: 2, total votos en contra: 0
B64: 0
B65: 0 comentarios
B66: PROPUESTA
B67: Seguridad de la información y priorización de la Nube
B68: Nicolás Schubert•hace 1 semana De acuerdo con la consulta ciudadana virtual para la Estrategia de Gestión de Datos del Estado del Gobierno de Chile (“EGDE”), a continuación, se presentan los comentarios de Google Cloud Hispanoamérica que consideramos pueden resultar constructivos para esta iniciativa de la División de Gobierno Digital de la Secretaría General de la Presidencia. Sistema de gestión de datos: seguridad de la informaciónTeniendo en cuenta el objetivo de gestionar eficazmente los datos para generar valor al interior de las instituciones y la ciudadanía contenido el EGDE, consideramos pertinente incluir los siguientes elementos como parte integral del diseño e implementación de esta estrategia: Libre flujo de datos: Con el fin de aprovechar al máximo las herramientas de innovación de analítica de datos y otras herramientas tecnológicas de gestión de datos resulta imperativo la aplicación de principios y marcos internacionales que garanticen el flujo transfronterizo de datos. Esta aproximación permite a las diferentes entidades del gobierno implementar soluciones basadas en la nube que, por sus características, resultan escalables e innovadoras. Privacidad y ciberseguridad: En concordancia con el punto anterior, la utilización de tecnologías exponenciales para la modernización del Estado debe estar basada en la confianza de los ciudadanos y los diferentes agentes que hacen parte de este proceso a través de principios de privacidad y ciberseguridad. En cuanto a la aplicación del principio de privacidad la estructuración de un sistema de clasificación de datos que determine el nivel de confidencialidad y reserva de la información permite consolidar un escenario de límites claros para los titulares y los diferentes agentes. En cuanto al principio de ciberseguridad, implementar estrategias para proteger la información de las personas, entidades y organizaciones resulta fundamental hoy en día. Para ello, se debe considerar que la seguridad de la información es transversal a todos los procesos y dependencias de gestión de información por lo que debe ser tratada a través de una óptica de prevención. Priorizar un enfoque preventivo requiere que los gobiernos promuevan y utilicen productos y servicios más seguros y no necesariamente productos y servicios de seguridad. Nube PrimeroLa computación en la Nube es una tecnología esencial de infraestructura y plataforma que permite acceder a productos y servicios escalables con ventajas competitivas de ahorros y tendientes a la gestión y gobernanza efectiva de los datos. Es por esto que establecer de forma expresa la preferencia de la Nube como un mecanismo que ofrece mayor seguridad y diferentes beneficios para la estructuración de arquitectura de datos de los gobiernos es un elemento fundamental para habilitar el máximo potencial de las tecnologías exponenciales en todas las entidades del gobierno, facilitando sistemas interoperables que permitan economías de escala y colaboración en los procesos internos de las organizaciones.
B69: Total votos a favor: 2, total votos en contra: 0
B70: 0
B71: 0 comentarios
B72: PROPUESTA
B73: Análisis de datos, estructura y herramientas
B75: Jorge Castro•hace 1 semana ¿Es posible una gobernanza de datos? Identificar estándares internacionales y procesos que permitan una alta calidad de los datos a gobernar, así cómo revisión de los procesos de obtención de ellos¿Es posible un maestro de datos?Considerando que los datos deben estar innominados e indeterminados al menos, sería difícil generar un maestro, sin embargo, si cumplen las mínimas restricciones de seguridad, sería posible publicar datos que permitan análisis de ellos.Creación de un proceso de análisis de datos "estilo nacional, ¿estamos preparados?"Es posible identificar y enseñar a la ciudadanía los pasos para realizar un correcto análisis de datos, creando los pasos necesarios recopilar, transformar, analizar y visualizar datos utilizando herramientas y tecnologías relevantes y cuidado del repositorio, para que todo ciudadano entienda el manejo de datos como un activo. La idea con todo esto, es poder otorgar la información para toda la ciudadanía, otorgando además herramientas para usar esta información, ya que hasta ahora pareciera que está solo disponible para ciudadanos con altos niveles de estudios, el resto no se siente apto para hacer análisis de datos, porque faltan estas herramientas.
B76: Total votos a favor: 1, total votos en contra: 0
B77: 1
B78: ningún comentario
B79: PROPUESTA
B80: Una interoperabilidad con mayor transparencia para la ciudadanía
B82: Camilo Isaí Saldías Robles•hace 1 semana El “Documento de Política - Líneas de Acción: Propuesta de Estrategia de Gestión de Datos del Estado” que se ofrece a consulta pública muestra un excelente avance hacia una política de Estado en la materia.Si bien División de Gobierno Digital contempla entre sus tareas identificar oportunidades de mejora para modernizar y digitalizar la administración del Estado, sería recomendable enfatizar y explicitar como visión la construcción de un gobierno digital centrado en la persona humana.Como referencia de esta deseable visión puede destacarse la experiencia de Estonia. Notablemente, este país lanzó en 2021 un Plan de Desarrollo de una Sociedad Digital (Digiühiskonna Arengukava) para 2030, el cual incluye al gobierno digital en armonía con a otros componentes, como la ciberseguridad y la conectividad. En este contexto, se identifica que la transparencia en el procesamiento de datos y la promoción de derechos fundamentales son factores claves para lograr una real confianza de la ciudadanía en las instituciones públicas.En esta línea, es posible destacar dos medidas adoptadas por Estonia. Por un lado, el “Portal del Paciente” (Patsiendiportaal) permite a las personas consultar su ficha médica según los datos aportados por sus proveedores de servicios de salud (públicos y privados) y reservar horas médicas en centros de salud; incluso, es posible visualizar la ubicación geográfica de los casos activos de Covid-19. Por otro lado, se ha avanzado en la implementación de un “Rastreador de Datos” (Andmejälgija) que permite a las personas visualizar de manera general qué operaciones se han realizado con sus datos personales. Cabe destacar que ambas medidas se integran dentro de un portal único (www.eesti.ee) y que su condición habilitante es una identidad digital unitaria, integrada y segura.Además, se observa que esta transparencia mejora la experiencia del usuario de los servicios públicos y comunica con mayor fuerza el sentido de utilidad de la modernización digital, siendo un refuerzo positivo para el proceso de gestión del cambio entre los funcionarios públicos y un cambio cultural más amplio en la sociedad.En consecuencia, es recomendable enriquecer el enfoque actual que la Propuesta contempla para la interoperabilidad de elementos (datos, documentos y expedientes) con la visualización de una infraestructura y mecanismos transversales que aseguren una transparencia robusta para las personas del tratamiento de sus datos personales, de forma tal que se fortalezca la accountability de estos procesos. Esto cumplirá además un rol clave frente a la gradual incorporación del uso de inteligencia artificial en la toma de decisiones. De esta manera, poniendo a las personas en el centro, se puede promover un diálogo más fructífero entre la ciudadanía y la administración pública que sea respetuoso de los derechos fundamentales y mejore la confianza en las instituciones.Camilo SaldíasAbogadoMA en Derecho Informático, Universidad de Tartu, Estonia.-
B83: Total votos a favor: 1, total votos en contra: 0
B84: 1
B85: ningún comentario
B86: PROPUESTA
B87: Procesamiento Automatizado de Datos Abiertos
B89: Hernan Espinoza•hace 1 semana Creo que es importante que se busque fomentar el uso de los datos abiertos, preparándolos en formato y calidad, para ser utilizados por sistemas de procesamiento basados en inteligencia Artificial, modelos de lenguajes, para ayudar al desarrollo de la próxima generación de aplicación estado ciudadanas.Esta nueva generación de aplicación y sistemas de interacción con el estado podría ofrecer asistentes virtuales o resolutores de problemas personalizados según el perfil del ciudadano, pudiendo mejorar la cercanía, el lenguaje, y el nivel de detalles para orientar o responder a las consultas de los ciudadanos.Se podrían mejorar los sistemas de clasificación de la población, y mejorar en base estas agrupaciones, las políticas publicas que vayan en respuesta a sus necesidades.Facilitar el acceso de los datos a los centros de pensamiento y universidades es un deber que puede beneficiar a la sociedad, pero siempre teniendo a la vista los potenciales riesgos de un mal uso (como ya se ha visto).Toda política pública debe ser coordinada con el ecosistema de políticas públicas, que tengan relación. En este orden de ideas, se debiera buscar las relaciones y sinergias pertinentes con la nueva Política Nacional de Inteligencia artificial y con la Nueva Política Nacional de Ciberseguridad, al menos.
B90: Total votos a favor: 1, total votos en contra: 0
B91: 1
B92: ningún comentario
B93: PROPUESTA
B94: Maestros de Datos
B95: Leonardo Arancibia•hace 1 semana Me parece necesario que dentro de la estrategia se mencione que se definirán maestros de datos a nivel nacional y quien será el responsable (institución) de su gobernanza, actualización y proceso global., esto implica por ejemplo, datos de contactabilidad y cual será la fuente primaria del estado. Hoy en día de manera local, se generan mucha información que no se centraliza y se genera una fuente principal donde puedan consumir información las distintas instituciones del estado.Se debe dejar claro en documento que toda institución pública tendrá la obligatoriedad de generar los mecanismos de integración necesarios, de la información que genere, resguardando los principios de confidencialidad que apliquen y seguridad de la información.Se deben definir estándares mínimos de interoperabilidad, como también componentes mínimos de soporte y uptimeEl análisis de todo este proceso debe ser realizado con una mirada de diseño de servicios, que pretenda priorizar los datos necesarios para nuestra población e instituciones que permita avanzar a interoperar con dichas areas.
B96: Total votos a favor: 5, total votos en contra: 0
B97: 2
B98: 2 comentarios
B99: PROPUESTA
B100: Comentarios a borrador Estrategia de Datos del Estado
B102: Pablo Galaz•hace 1 semana A continuación, se lista una serie de comentarios al borrador de Estrategia de gestión de Datos del Estado, elaborados por colaboradores del Centro del Sistemas Públicos (Departamento de Ingeniería Industrial - U. de Chile), sin representar necesariamente la opinión institucional sobre la Estrategia en cuestión. En relación a sección 1 (Introducción), no e hace referencia al valor económico de los datos, algunos ejemplo: lo que está haciendo Europa (https://www.alejandrobarros.com/datos-abiertos-en-europa-mejoran/) Valor Económico de los datos (https://www.alejandrobarros.com/el-valor-economico-de-los-datos/). Asimismo, no se hace mención a la necesidad de contar una adecuada alfabetización numérica en el servicio público para que los datos puedan encontrar valor. En relación a la sección 2 (Contexto), algunos comentarios. Primero, se hace referencia a la ley de Transformación Digital con una la lógica de digitalizar, y no de transformar. Segundo, no hay referencia al incremento del volumen de datos en soporte digital y su convivencia durante años con soporte papel. Tercero, no hay referencia explícita al proyecto de ley que modifica la ley de transparencia. Cuarto, no se hace referencia a algunos usos de datos por parte del Estado: IoT, Big Data e IA (solo se mencionan las tecnologías). Y quinto, no hay un adecuado análisis de interoperabilidad entre modelo centralizados (PISEE 1.0) y descentralizados. En la sección 3.2 (Alcance), no hay referencias al marco legal de acceso a la información pública y de ciberseguridad que son parte del tema. En la sección 3.3 (Ciclo de valor de la gestión de datos) se debe considerar el ciclo de vida de la Información ILCM, y se requiere explicitar la fuente del diagramo de ciclo de valor. En la sección 3.4 (Niveles de la Estrategia), específicamente en el Nivel 1 de Estrategia, se sugiere explicitar que los datos a generar y recoger deben ser priorizados en función de preguntas o decisiones que buscan ser informadas. No se trata de recolectar todo, lo cual puede ser contraproducente. En relación al Nivel 2, se comenta que la colaboración interinstitucional suena bien pero es débil no existe un ente coordinador que tenga dependencia jerárquica sobre el resto de instituciones en lo que se refiere a datos del Estado. Algo así como un Network Administrative Organization. Caso contrario, quedaría a criterio de cada institución la relevancia estratégica de disponer (o no) ciertos datos. Adicionalmente, sobre el mismo Nivel 2, se comenta que se requiere incorporar la participación de entidades privadas y academia en el ecosistema a fin que puedan interiorizarse sobre el uso de plataformas transversales del Estado (SIGFE) y servicios para digitalización (ej.: SIMPLE), en el entendido que las entidades públicas también puedan pedir ayuda a actores fuera del sector público para llevar a cabo sus estrategias de datos (desde infraestructura hasta digitalización de procedimientos). En la sección 3.4.1 (Estrategia a nivel de organismos), se debe hacer énfasis respecto a qué tipo de decisiones serán revisadas a la luz de las brechas que identifiquen los servicios y que se sistematizarán vía instrumentos creados por SEGPRES (ej.: categorizar las brechas, identificar sinergias de inversión entre servicios, etc.). Adicionalmente, se comenta que los frameworks de arquitectura no está correctamente señalados (para más información ver: https://www.alejandrobarros.com/arquitecturas-empresariales-en-el-sector-publico/). Importante señalar que TOGAF no es la única aproximación neutral respecto del proveedor. En la sección 3.4.3.1 (Modelo federado de datos) señalar que un modelo federado de datos solo se entra en la dimensión de interoperabilidad (uso), pero no hay una bajada en las otras etapas del ciclo de valor datos (Figura 1). Además, no se contempla a organismos de la sociedad civil como "Consumidores" da datos. O al menos no es explícito. Existen poco servicios públicos que cuentan con APIs que permiten acceder de forma externa a bases de datos administradas por el Estado. En la sección 4 (Gobernanza), el documento deja de lado varias de sus dimensiones relevantes (ver Meuleman 2006, https://www.alejandrobarros.com/algunas-ideas-para-la-gobernanza-de-la-transformacion-digital/) En la sección 4.1 (Gobernanza a nivel de organismos), el rol de Encargado de Gestión de Datos tiene una descripción poco clara. Además, la capacidad del Encargado se verá limitada de acuerdo al nivel jerárquico de quien asuma el rol. De no explicitarse lo anterior, pueden darse desbalances entre los mismos servicios. En la sección 4.3.3 (Plataforma de seguimiento para la implementación de la Estrategia), se sugiere incorporar aprendizajes en base a la experiencia del portal donde se monitorea el avance de la implementación del Registro Nacional de Trámites. En particular, se sugiere revisar "el ciclo de vida" de lo que se entenderá por "iniciativas comprometidas", en el entendido que estas pueden modificarse, ajustarse, eliminarse, fusionarse, etc. Y todo eso, actualmente no es capturado por el sistema de seguimiento del RNT. En la sección 5.2 (Hoja de Ruta), la hoja de ruta son literalmente solo iniciativa de corto plazo (salvo una). Si es así, conceptualmente no es una Hoja de ruta porque no muestra un orden de prioridad, siendo más bien un listado de "cosas por hacer".
B103: Total votos a favor: 2, total votos en contra: 0
B104: 1
B105: ningún comentario
B106: PROPUESTA
B107: Enfoque del Dato como Producto
B109: Jennifer Andrea Alvarez Flores•hace 1 semana Logré visualizar en el documento sólo 2 veces la palabra "producto", pero en ningún caso ligado al dato como producto. A qué me refiero con esto: desde una perspectiva que he estado estudiando, surge el concepto de "productos de datos". Imaginemos esta estrategia que contemple este nuevo enfoque donde los datos son tratados como productos en sí mismos, con su propia arquitectura, evolución y responsables que se dedican a ello. Pongo un ejemplo relacionado a mi lugar de trabajo, si tengo una cartera de contribuyentes morosos, cuando hablamos del gobierno de productos de datos me refiero a soluciones concretas tales como un cuadro de mando integral o una segmentación detallada de esos usuarios según la deuda. Cada uno de esos productos de datos, debe cumplir diversos requisitos para que sean gobernados adecuadamente. ¿Cómo qué? en primer lugar, documentando una arquitectura del producto de datos, comprendiendo la estructura, integración y cómo se almacenan, lo que nos ayudará a formar una base sólida para el correcto desarrollo y mantenimiento del producto de datos. Otro aspecto puede ser que el código esté muy bien documentado también, registrando las metodologías que se utilicen. Junto con lo anterior es clave el data owner o un data steward designado para cada producto de datos, ya que será el responsable de garantizar la calidad del producto y coordinar su desarrollo continuo.A qué quiero llegar, que si bien me parece que la propuesta inicial para una estrategia del dato es muy buena, el gobierno de datos por sí solo no es suficiente, y la podemos complementar con esta nueva pieza de gobernanza de los productos de los datos que propongo, así tratamos todo como un conjunto, maximizamos su valor, podemos pensar en una mayor trazabilidad y continuidad de lo que se haga o transforme. Esto claramente es escalable a todo aspecto y organización, ya sea pública o privada y en algún momento se debería ver la forma de hacer converger ambos mundos.Además, sugiero que esto logre avanzar más y se puedan tocar en el documento, lo que es Data Mesh y Data Fabric. Estos 2 conceptos proponen enfoque organizativo de descentralización y arquitecturas de integración. Desafíos que no podemos perder de vista en un corto plazo en temas de datos, que va cambiando y moviéndose día a día. Me gustaría ver un Estado a la vanguardia mundial en estos temas.Espero les parezca bien mi aporte y felicitar por el muy buen trabajo que están liderando. Quedo a su disposición para lo que se necesite colaborar. Saludos.
B110: Total votos a favor: 11, total votos en contra: 0
B111: 2
B112: 2 comentarios
B113: PROPUESTA
B114: Comentarios al documento Propuesta de Estrategia de Gestión de Datos del Estado
...

Sheet Resumen_Norm

Sheet Resumen_Obl
